{
  "verses" : [ {
    "id" : 2161,
    "verse_number" : 21,
    "verse_key" : "18:21",
    "hizb_number" : 30,
    "rub_el_hizb_number" : 118,
    "ruku_number" : 254,
    "manzil_number" : 4,
    "sajdah_number" : null,
    "text_uthmani" : "وَكَذَٰلِكَ أَعْثَرْنَا عَلَيْهِمْ لِيَعْلَمُوٓا۟ أَنَّ وَعْدَ ٱللَّهِ حَقٌّ وَأَنَّ ٱلسَّاعَةَ لَا رَيْبَ فِيهَآ إِذْ يَتَنَـٰزَعُونَ بَيْنَهُمْ أَمْرَهُمْ ۖ فَقَالُوا۟ ٱبْنُوا۟ عَلَيْهِم بُنْيَـٰنًا ۖ رَّبُّهُمْ أَعْلَمُ بِهِمْ ۚ قَالَ ٱلَّذِينَ غَلَبُوا۟ عَلَىٰٓ أَمْرِهِمْ لَنَتَّخِذَنَّ عَلَيْهِم مَّسْجِدًا",
    "chapter_id" : 18,
    "text_imlaei_simple" : "وكذلك اعثرنا عليهم ليعلموا ان وعد الله حق وان الساعة لا ريب فيها اذ يتنازعون بينهم امرهم فقالوا ابنوا عليهم بنيانا ربهم اعلم بهم قال الذين غلبوا على امرهم لنتخذن عليهم مسجدا",
    "page_number" : 296,
    "juz_number" : 15,
    "words" : [ {
      "id" : 23497,
      "position" : 1,
      "audio_url" : "wbw/018_021_001.mp3",
      "verse_key" : "18:21",
      "verse_id" : 2161,
      "location" : "18:21:1",
      "text_uthmani" : "وَكَذَٰلِكَ",
      "code_v1" : "ﭑ",
      "qpc_uthmani_hafs" : "وَكَذَٰلِكَ",
      "char_type_name" : "word",
      "page_number" : 296,
      "line_number" : 1,
      "text" : "ﭑ",
      "translation" : {
        "text" : "And similarly",
        "language_name" : "english",
        "language_id" : 38
      },
      "transliteration" : {
        "text" : "wakadhālika",
        "language_name" : "english",
        "language_id" : 38
      }
    }, {
      "id" : 23498,
      "position" : 2,
      "audio_url" : "wbw/018_021_002.mp3",
      "verse_key" : "18:21",
      "verse_id" : 2161,
      "location" : "18:21:2",
      "text_uthmani" : "أَعْثَرْنَا",
      "code_v1" : "ﭒ",
      "qpc_uthmani_hafs" : "أَعۡثَرۡنَا",
      "char_type_name" : "word",
      "page_number" : 296,
      "line_number" : 1,
      "text" : "ﭒ",
      "translation" : {
        "text" : "We made known",
        "language_name" : "english",
        "language_id" : 38
      },
      "transliteration" : {
        "text" : "aʿtharnā",
        "language_name" : "english",
        "language_id" : 38
      }
    }, {
      "id" : 23499,
      "position" : 3,
      "audio_url" : "wbw/018_021_003.mp3",
      "verse_key" : "18:21",
      "verse_id" : 2161,
      "location" : "18:21:3",
      "text_uthmani" : "عَلَيْهِمْ",
      "code_v1" : "ﭓ",
      "qpc_uthmani_hafs" : "عَلَيۡهِمۡ",
      "char_type_name" : "word",
      "page_number" : 296,
      "line_number" : 1,
      "text" : "ﭓ",
      "translation" : {
        "text" : "about them",
        "language_name" : "english",
        "language_id" : 38
      },
      "transliteration" : {
        "text" : "ʿalayhim",
        "language_name" : "english",
        "language_id" : 38
      }
    }, {
      "id" : 23500,
      "position" : 4,
      "audio_url" : "wbw/018_021_004.mp3",
      "verse_key" : "18:21",
      "verse_id" : 2161,
      "location" : "18:21:4",
      "text_uthmani" : "لِيَعْلَمُوٓا۟",
      "code_v1" : "ﭔ",
      "qpc_uthmani_hafs" : "لِيَعۡلَمُوٓاْ",
      "char_type_name" : "word",
      "page_number" : 296,
      "line_number" : 1,
      "text" : "ﭔ",
      "translation" : {
        "text" : "that they might know",
        "language_name" : "english",
        "language_id" : 38
      },
      "transliteration" : {
        "text" : "liyaʿlamū",
        "language_name" : "english",
        "language_id" : 38
      }
    }, {
      "id" : 23501,
      "position" : 5,
      "audio_url" : "wbw/018_021_005.mp3",
      "verse_key" : "18:21",
      "verse_id" : 2161,
      "location" : "18:21:5",
      "text_uthmani" : "أَنَّ",
      "code_v1" : "ﭕ",
      "qpc_uthmani_hafs" : "أَنَّ",
      "char_type_name" : "word",
      "page_number" : 296,
      "line_number" : 1,
      "text" : "ﭕ",
      "translation" : {
        "text" : "that",
        "language_name" : "english",
        "language_id" : 38
      },
      "transliteration" : {
        "text" : "anna",
        "language_name" : "english",
        "language_id" : 38
      }
    }, {
      "id" : 23502,
      "position" : 6,
      "audio_url" : "wbw/018_021_006.mp3",
      "verse_key" : "18:21",
      "verse_id" : 2161,
      "location" : "18:21:6",
      "text_uthmani" : "وَعْدَ",
      "code_v1" : "ﭖ",
      "qpc_uthmani_hafs" : "وَعۡدَ",
      "char_type_name" : "word",
      "page_number" : 296,
      "line_number" : 1,
      "text" : "ﭖ",
      "translation" : {
        "text" : "(the) Promise",
        "language_name" : "english",
        "language_id" : 38
      },
      "transliteration" : {
        "text" : "waʿda",
        "language_name" : "english",
        "language_id" : 38
      }
    }, {
      "id" : 23503,
      "position" : 7,
      "audio_url" : "wbw/018_021_007.mp3",
      "verse_key" : "18:21",
      "verse_id" : 2161,
      "location" : "18:21:7",
      "text_uthmani" : "ٱللَّهِ",
      "code_v1" : "ﭗ",
      "qpc_uthmani_hafs" : "ٱللَّهِ",
      "char_type_name" : "word",
      "page_number" : 296,
      "line_number" : 1,
      "text" : "ﭗ",
      "translation" : {
        "text" : "(of) Allah",
        "language_name" : "english",
        "language_id" : 38
      },
      "transliteration" : {
        "text" : "l-lahi",
        "language_name" : "english",
        "language_id" : 38
      }
    }, {
      "id" : 23504,
      "position" : 8,
      "audio_url" : "wbw/018_021_008.mp3",
      "verse_key" : "18:21",
      "verse_id" : 2161,
      "location" : "18:21:8",
      "text_uthmani" : "حَقٌّۭ",
      "code_v1" : "ﭘ",
      "qpc_uthmani_hafs" : "حَقّٞ",
      "char_type_name" : "word",
      "page_number" : 296,
      "line_number" : 1,
      "text" : "ﭘ",
      "translation" : {
        "text" : "(is) true",
        "language_name" : "english",
        "language_id" : 38
      },
      "transliteration" : {
        "text" : "ḥaqqun",
        "language_name" : "english",
        "language_id" : 38
      }
    }, {
      "id" : 23505,
      "position" : 9,
      "audio_url" : "wbw/018_021_009.mp3",
      "verse_key" : "18:21",
      "verse_id" : 2161,
      "location" : "18:21:9",
      "text_uthmani" : "وَأَنَّ",
      "code_v1" : "ﭙ",
      "qpc_uthmani_hafs" : "وَأَنَّ",
      "char_type_name" : "word",
      "page_number" : 296,
      "line_number" : 1,
      "text" : "ﭙ",
      "translation" : {
        "text" : "and that",
        "language_name" : "english",
        "language_id" : 38
      },
      "transliteration" : {
        "text" : "wa-anna",
        "language_name" : "english",
        "language_id" : 38
      }
    }, {
      "id" : 23506,
      "position" : 10,
      "audio_url" : "wbw/018_021_010.mp3",
      "verse_key" : "18:21",
      "verse_id" : 2161,
      "location" : "18:21:10",
      "text_uthmani" : "ٱلسَّاعَةَ",
      "code_v1" : "ﭚ",
      "qpc_uthmani_hafs" : "ٱلسَّاعَةَ",
      "char_type_name" : "word",
      "page_number" : 296,
      "line_number" : 2,
      "text" : "ﭚ",
      "translation" : {
        "text" : "(about) the Hour",
        "language_name" : "english",
        "language_id" : 38
      },
      "transliteration" : {
        "text" : "l-sāʿata",
        "language_name" : "english",
        "language_id" : 38
      }
    }, {
      "id" : 23507,
      "position" : 11,
      "audio_url" : "wbw/018_021_011.mp3",
      "verse_key" : "18:21",
      "verse_id" : 2161,
      "location" : "18:21:11",
      "text_uthmani" : "لَا",
      "code_v1" : "ﭛ",
      "qpc_uthmani_hafs" : "لَا",
      "char_type_name" : "word",
      "page_number" : 296,
      "line_number" : 2,
      "text" : "ﭛ",
      "translation" : {
        "text" : "(there is) no",
        "language_name" : "english",
        "language_id" : 38
      },
      "transliteration" : {
        "text" : "lā",
        "language_name" : "english",
        "language_id" : 38
      }
    }, {
      "id" : 23508,
      "position" : 12,
      "audio_url" : "wbw/018_021_012.mp3",
      "verse_key" : "18:21",
      "verse_id" : 2161,
      "location" : "18:21:12",
      "text_uthmani" : "رَيْبَ",
      "code_v1" : "ﭜ",
      "qpc_uthmani_hafs" : "رَيۡبَ",
      "char_type_name" : "word",
      "page_number" : 296,
      "line_number" : 2,
      "text" : "ﭜ",
      "translation" : {
        "text" : "doubt",
        "language_name" : "english",
        "language_id" : 38
      },
      "transliteration" : {
        "text" : "rayba",
        "language_name" : "english",
        "language_id" : 38
      }
    }, {
      "id" : 23509,
      "position" : 13,
      "audio_url" : "wbw/018_021_013.mp3",
      "verse_key" : "18:21",
      "verse_id" : 2161,
      "location" : "18:21:13",
      "text_uthmani" : "فِيهَآ",
      "code_v1" : "ﭝ",
      "qpc_uthmani_hafs" : "فِيهَآ",
      "char_type_name" : "word",
      "page_number" : 296,
      "line_number" : 2,
      "text" : "ﭝ",
      "translation" : {
        "text" : "in it",
        "language_name" : "english",
        "language_id" : 38
      },
      "transliteration" : {
        "text" : "fīhā",
        "language_name" : "english",
        "language_id" : 38
      }
    }, {
      "id" : 23510,
      "position" : 14,
      "audio_url" : "wbw/018_021_014.mp3",
      "verse_key" : "18:21",
      "verse_id" : 2161,
      "location" : "18:21:14",
      "text_uthmani" : "إِذْ",
      "code_v1" : "ﭞ",
      "qpc_uthmani_hafs" : "إِذۡ",
      "char_type_name" : "word",
      "page_number" : 296,
      "line_number" : 2,
      "text" : "ﭞ",
      "translation" : {
        "text" : "When",
        "language_name" : "english",
        "language_id" : 38
      },
      "transliteration" : {
        "text" : "idh",
        "language_name" : "english",
        "language_id" : 38
      }
    }, {
      "id" : 23511,
      "position" : 15,
      "audio_url" : "wbw/018_021_015.mp3",
      "verse_key" : "18:21",
      "verse_id" : 2161,
      "location" : "18:21:15",
      "text_uthmani" : "يَتَنَـٰزَعُونَ",
      "code_v1" : "ﭟ",
      "qpc_uthmani_hafs" : "يَتَنَٰزَعُونَ",
      "char_type_name" : "word",
      "page_number" : 296,
      "line_number" : 2,
      "text" : "ﭟ",
      "translation" : {
        "text" : "they disputed",
        "language_name" : "english",
        "language_id" : 38
      },
      "transliteration" : {
        "text" : "yatanāzaʿūna",
        "language_name" : "english",
        "language_id" : 38
      }
    }, {
      "id" : 23512,
      "position" : 16,
      "audio_url" : "wbw/018_021_016.mp3",
      "verse_key" : "18:21",
      "verse_id" : 2161,
      "location" : "18:21:16",
      "text_uthmani" : "بَيْنَهُمْ",
      "code_v1" : "ﭠ",
      "qpc_uthmani_hafs" : "بَيۡنَهُمۡ",
      "char_type_name" : "word",
      "page_number" : 296,
      "line_number" : 2,
      "text" : "ﭠ",
      "translation" : {
        "text" : "among themselves",
        "language_name" : "english",
        "language_id" : 38
      },
      "transliteration" : {
        "text" : "baynahum",
        "language_name" : "english",
        "language_id" : 38
      }
    }, {
      "id" : 23513,
      "position" : 17,
      "audio_url" : "wbw/018_021_017.mp3",
      "verse_key" : "18:21",
      "verse_id" : 2161,
      "location" : "18:21:17",
      "text_uthmani" : "أَمْرَهُمْ ۖ",
      "code_v1" : "ﭡﭢ",
      "qpc_uthmani_hafs" : "أَمۡرَهُمۡۖ",
      "char_type_name" : "word",
      "page_number" : 296,
      "line_number" : 2,
      "text" : "ﭡﭢ",
      "translation" : {
        "text" : "about their affair",
        "language_name" : "english",
        "language_id" : 38
      },
      "transliteration" : {
        "text" : "amrahum",
        "language_name" : "english",
        "language_id" : 38
      }
    }, {
      "id" : 23515,
      "position" : 18,
      "audio_url" : "wbw/018_021_019.mp3",
      "verse_key" : "18:21",
      "verse_id" : 2161,
      "location" : "18:21:18",
      "text_uthmani" : "فَقَالُوا۟",
      "code_v1" : "ﭣ",
      "qpc_uthmani_hafs" : "فَقَالُواْ",
      "char_type_name" : "word",
      "page_number" : 296,
      "line_number" : 2,
      "text" : "ﭣ",
      "translation" : {
        "text" : "and they said",
        "language_name" : "english",
        "language_id" : 38
      },
      "transliteration" : {
        "text" : "faqālū",
        "language_name" : "english",
        "language_id" : 38
      }
    }, {
      "id" : 23516,
      "position" : 19,
      "audio_url" : "wbw/018_021_020.mp3",
      "verse_key" : "18:21",
      "verse_id" : 2161,
      "location" : "18:21:19",
      "text_uthmani" : "ٱبْنُوا۟",
      "code_v1" : "ﭤ",
      "qpc_uthmani_hafs" : "ٱبۡنُواْ",
      "char_type_name" : "word",
      "page_number" : 296,
      "line_number" : 3,
      "text" : "ﭤ",
      "translation" : {
        "text" : "Construct",
        "language_name" : "english",
        "language_id" : 38
      },
      "transliteration" : {
        "text" : "ib'nū",
        "language_name" : "english",
        "language_id" : 38
      }
    }, {
      "id" : 23517,
      "position" : 20,
      "audio_url" : "wbw/018_021_021.mp3",
      "verse_key" : "18:21",
      "verse_id" : 2161,
      "location" : "18:21:20",
      "text_uthmani" : "عَلَيْهِم",
      "code_v1" : "ﭥ",
      "qpc_uthmani_hafs" : "عَلَيۡهِم",
      "char_type_name" : "word",
      "page_number" : 296,
      "line_number" : 3,
      "text" : "ﭥ",
      "translation" : {
        "text" : "over them",
        "language_name" : "english",
        "language_id" : 38
      },
      "transliteration" : {
        "text" : "ʿalayhim",
        "language_name" : "english",
        "language_id" : 38
      }
    }, {
      "id" : 23518,
      "position" : 21,
      "audio_url" : "wbw/018_021_022.mp3",
      "verse_key" : "18:21",
      "verse_id" : 2161,
      "location" : "18:21:21",
      "text_uthmani" : "بُنْيَـٰنًۭا ۖ",
      "code_v1" : "ﭦﭧ",
      "qpc_uthmani_hafs" : "بُنۡيَٰنٗاۖ",
      "char_type_name" : "word",
      "page_number" : 296,
      "line_number" : 3,
      "text" : "ﭦﭧ",
      "translation" : {
        "text" : "a structure",
        "language_name" : "english",
        "language_id" : 38
      },
      "transliteration" : {
        "text" : "bun'yānan",
        "language_name" : "english",
        "language_id" : 38
      }
    }, {
      "id" : 23520,
      "position" : 22,
      "audio_url" : "wbw/018_021_024.mp3",
      "verse_key" : "18:21",
      "verse_id" : 2161,
      "location" : "18:21:22",
      "text_uthmani" : "رَّبُّهُمْ",
      "code_v1" : "ﭨ",
      "qpc_uthmani_hafs" : "رَّبُّهُمۡ",
      "char_type_name" : "word",
      "page_number" : 296,
      "line_number" : 3,
      "text" : "ﭨ",
      "translation" : {
        "text" : "Their Lord",
        "language_name" : "english",
        "language_id" : 38
      },
      "transliteration" : {
        "text" : "rabbuhum",
        "language_name" : "english",
        "language_id" : 38
      }
    }, {
      "id" : 23521,
      "position" : 23,
      "audio_url" : "wbw/018_021_025.mp3",
      "verse_key" : "18:21",
      "verse_id" : 2161,
      "location" : "18:21:23",
      "text_uthmani" : "أَعْلَمُ",
      "code_v1" : "ﭩ",
      "qpc_uthmani_hafs" : "أَعۡلَمُ",
      "char_type_name" : "word",
      "page_number" : 296,
      "line_number" : 3,
      "text" : "ﭩ",
      "translation" : {
        "text" : "knows best",
        "language_name" : "english",
        "language_id" : 38
      },
      "transliteration" : {
        "text" : "aʿlamu",
        "language_name" : "english",
        "language_id" : 38
      }
    }, {
      "id" : 23522,
      "position" : 24,
      "audio_url" : "wbw/018_021_026.mp3",
      "verse_key" : "18:21",
      "verse_id" : 2161,
      "location" : "18:21:24",
      "text_uthmani" : "بِهِمْ ۚ",
      "code_v1" : "ﭪﭫ",
      "qpc_uthmani_hafs" : "بِهِمۡۚ",
      "char_type_name" : "word",
      "page_number" : 296,
      "line_number" : 3,
      "text" : "ﭪﭫ",
      "translation" : {
        "text" : "about them",
        "language_name" : "english",
        "language_id" : 38
      },
      "transliteration" : {
        "text" : "bihim",
        "language_name" : "english",
        "language_id" : 38
      }
    }, {
      "id" : 23524,
      "position" : 25,
      "audio_url" : "wbw/018_021_028.mp3",
      "verse_key" : "18:21",
      "verse_id" : 2161,
      "location" : "18:21:25",
      "text_uthmani" : "قَالَ",
      "code_v1" : "ﭬ",
      "qpc_uthmani_hafs" : "قَالَ",
      "char_type_name" : "word",
      "page_number" : 296,
      "line_number" : 3,
      "text" : "ﭬ",
      "translation" : {
        "text" : "Said",
        "language_name" : "english",
        "language_id" : 38
      },
      "transliteration" : {
        "text" : "qāla",
        "language_name" : "english",
        "language_id" : 38
      }
    }, {
      "id" : 23525,
      "position" : 26,
      "audio_url" : "wbw/018_021_029.mp3",
      "verse_key" : "18:21",
      "verse_id" : 2161,
      "location" : "18:21:26",
      "text_uthmani" : "ٱلَّذِينَ",
      "code_v1" : "ﭭ",
      "qpc_uthmani_hafs" : "ٱلَّذِينَ",
      "char_type_name" : "word",
      "page_number" : 296,
      "line_number" : 3,
      "text" : "ﭭ",
      "translation" : {
        "text" : "those who",
        "language_name" : "english",
        "language_id" : 38
      },
      "transliteration" : {
        "text" : "alladhīna",
        "language_name" : "english",
        "language_id" : 38
      }
    }, {
      "id" : 23526,
      "position" : 27,
      "audio_url" : "wbw/018_021_030.mp3",
      "verse_key" : "18:21",
      "verse_id" : 2161,
      "location" : "18:21:27",
      "text_uthmani" : "غَلَبُوا۟",
      "code_v1" : "ﭮ",
      "qpc_uthmani_hafs" : "غَلَبُواْ",
      "char_type_name" : "word",
      "page_number" : 296,
      "line_number" : 3,
      "text" : "ﭮ",
      "translation" : {
        "text" : "prevailed",
        "language_name" : "english",
        "language_id" : 38
      },
      "transliteration" : {
        "text" : "ghalabū",
        "language_name" : "english",
        "language_id" : 38
      }
    }, {
      "id" : 23527,
      "position" : 28,
      "audio_url" : "wbw/018_021_031.mp3",
      "verse_key" : "18:21",
      "verse_id" : 2161,
      "location" : "18:21:28",
      "text_uthmani" : "عَلَىٰٓ",
      "code_v1" : "ﭯ",
      "qpc_uthmani_hafs" : "عَلَىٰٓ",
      "char_type_name" : "word",
      "page_number" : 296,
      "line_number" : 3,
      "text" : "ﭯ",
      "translation" : {
        "text" : "in",
        "language_name" : "english",
        "language_id" : 38
      },
      "transliteration" : {
        "text" : "ʿalā",
        "language_name" : "english",
        "language_id" : 38
      }
    }, {
      "id" : 23528,
      "position" : 29,
      "audio_url" : "wbw/018_021_032.mp3",
      "verse_key" : "18:21",
      "verse_id" : 2161,
      "location" : "18:21:29",
      "text_uthmani" : "أَمْرِهِمْ",
      "code_v1" : "ﭰ",
      "qpc_uthmani_hafs" : "أَمۡرِهِمۡ",
      "char_type_name" : "word",
      "page_number" : 296,
      "line_number" : 4,
      "text" : "ﭰ",
      "translation" : {
        "text" : "their matter",
        "language_name" : "english",
        "language_id" : 38
      },
      "transliteration" : {
        "text" : "amrihim",
        "language_name" : "english",
        "language_id" : 38
      }
    }, {
      "id" : 23529,
      "position" : 30,
      "audio_url" : "wbw/018_021_033.mp3",
      "verse_key" : "18:21",
      "verse_id" : 2161,
      "location" : "18:21:30",
      "text_uthmani" : "لَنَتَّخِذَنَّ",
      "code_v1" : "ﭱ",
      "qpc_uthmani_hafs" : "لَنَتَّخِذَنَّ",
      "char_type_name" : "word",
      "page_number" : 296,
      "line_number" : 4,
      "text" : "ﭱ",
      "translation" : {
        "text" : "Surely we will take",
        "language_name" : "english",
        "language_id" : 38
      },
      "transliteration" : {
        "text" : "lanattakhidhanna",
        "language_name" : "english",
        "language_id" : 38
      }
    }, {
      "id" : 23530,
      "position" : 31,
      "audio_url" : "wbw/018_021_034.mp3",
      "verse_key" : "18:21",
      "verse_id" : 2161,
      "location" : "18:21:31",
      "text_uthmani" : "عَلَيْهِم",
      "code_v1" : "ﭲ",
      "qpc_uthmani_hafs" : "عَلَيۡهِم",
      "char_type_name" : "word",
      "page_number" : 296,
      "line_number" : 4,
      "text" : "ﭲ",
      "translation" : {
        "text" : "over them",
        "language_name" : "english",
        "language_id" : 38
      },
      "transliteration" : {
        "text" : "ʿalayhim",
        "language_name" : "english",
        "language_id" : 38
      }
    }, {
      "id" : 23531,
      "position" : 32,
      "audio_url" : "wbw/018_021_035.mp3",
      "verse_key" : "18:21",
      "verse_id" : 2161,
      "location" : "18:21:32",
      "text_uthmani" : "مَّسْجِدًۭا",
      "code_v1" : "ﭳ",
      "qpc_uthmani_hafs" : "مَّسۡجِدٗا",
      "char_type_name" : "word",
      "page_number" : 296,
      "line_number" : 4,
      "text" : "ﭳ",
      "translation" : {
        "text" : "a place of worship",
        "language_name" : "english",
        "language_id" : 38
      },
      "transliteration" : {
        "text" : "masjidan",
        "language_name" : "english",
        "language_id" : 38
      }
    }, {
      "id" : 23532,
      "position" : 33,
      "audio_url" : null,
      "verse_key" : "18:21",
      "verse_id" : 2161,
      "location" : "18:21:33",
      "text_uthmani" : "٢١",
      "code_v1" : "ﭴ",
      "qpc_uthmani_hafs" : "٢١",
      "char_type_name" : "end",
      "page_number" : 296,
      "line_number" : 4,
      "text" : "ﭴ",
      "translation" : {
        "text" : "(21)",
        "language_name" : "english",
        "language_id" : 38
      },
      "transliteration" : {
        "text" : null,
        "language_name" : "english",
        "language_id" : 38
      }
    } ]
  }, {
    "id" : 2162,
    "verse_number" : 22,
    "verse_key" : "18:22",
    "hizb_number" : 30,
    "rub_el_hizb_number" : 118,
    "ruku_number" : 254,
    "manzil_number" : 4,
    "sajdah_number" : null,
    "text_uthmani" : "سَيَقُولُونَ ثَلَـٰثَةٌ رَّابِعُهُمْ كَلْبُهُمْ وَيَقُولُونَ خَمْسَةٌ سَادِسُهُمْ كَلْبُهُمْ رَجْمًۢا بِٱلْغَيْبِ ۖ وَيَقُولُونَ سَبْعَةٌ وَثَامِنُهُمْ كَلْبُهُمْ ۚ قُل رَّبِّىٓ أَعْلَمُ بِعِدَّتِهِم مَّا يَعْلَمُهُمْ إِلَّا قَلِيلٌ ۗ فَلَا تُمَارِ فِيهِمْ إِلَّا مِرَآءً ظَـٰهِرًا وَلَا تَسْتَفْتِ فِيهِم مِّنْهُمْ أَحَدًا",
    "chapter_id" : 18,
    "text_imlaei_simple" : "سيقولون ثلاثة رابعهم كلبهم ويقولون خمسة سادسهم كلبهم رجما بالغيب ويقولون سبعة وثامنهم كلبهم قل ربي اعلم بعدتهم ما يعلمهم الا قليل فلا تمار فيهم الا مراء ظاهرا ولا تستفت فيهم منهم احدا",
    "page_number" : 296,
    "juz_number" : 15,
    "words" : [ {
      "id" : 24531,
      "position" : 1,
      "audio_url" : "wbw/018_022_001.mp3",
      "verse_key" : "18:22",
      "verse_id" : 2162,
      "location" : "18:22:1",
      "text_uthmani" : "سَيَقُولُونَ",
      "code_v1" : "ﭵ",
      "qpc_uthmani_hafs" : "سَيَقُولُونَ",
      "char_type_name" : "word",
      "page_number" : 296,
      "line_number" : 4,
      "text" : "ﭵ",
      "translation" : {
        "text" : "They say",
        "language_name" : "english",
        "language_id" : 38
      },
      "transliteration" : {
        "text" : "sayaqūlūna",
        "language_name" : "english",
        "language_id" : 38
      }
    }, {
      "id" : 24532,
      "position" : 2,
      "audio_url" : "wbw/018_022_002.mp3",
      "verse_key" : "18:22",
      "verse_id" : 2162,
      "location" : "18:22:2",
      "text_uthmani" : "ثَلَـٰثَةٌۭ",
      "code_v1" : "ﭶ",
      "qpc_uthmani_hafs" : "ثَلَٰثَةٞ",
      "char_type_name" : "word",
      "page_number" : 296,
      "line_number" : 4,
      "text" : "ﭶ",
      "translation" : {
        "text" : "(they were) three",
        "language_name" : "english",
        "language_id" : 38
      },
      "transliteration" : {
        "text" : "thalāthatun",
        "language_name" : "english",
        "language_id" : 38
      }
    }, {
      "id" : 24533,
      "position" : 3,
      "audio_url" : "wbw/018_022_003.mp3",
      "verse_key" : "18:22",
      "verse_id" : 2162,
      "location" : "18:22:3",
      "text_uthmani" : "رَّابِعُهُمْ",
      "code_v1" : "ﭷ",
      "qpc_uthmani_hafs" : "رَّابِعُهُمۡ",
      "char_type_name" : "word",
      "page_number" : 296,
      "line_number" : 5,
      "text" : "ﭷ",
      "translation" : {
        "text" : "the forth of them",
        "language_name" : "english",
        "language_id" : 38
      },
      "transliteration" : {
        "text" : "rābiʿuhum",
        "language_name" : "english",
        "language_id" : 38
      }
    }, {
      "id" : 24534,
      "position" : 4,
      "audio_url" : "wbw/018_022_004.mp3",
      "verse_key" : "18:22",
      "verse_id" : 2162,
      "location" : "18:22:4",
      "text_uthmani" : "كَلْبُهُمْ",
      "code_v1" : "ﭸ",
      "qpc_uthmani_hafs" : "كَلۡبُهُمۡ",
      "char_type_name" : "word",
      "page_number" : 296,
      "line_number" : 5,
      "text" : "ﭸ",
      "translation" : {
        "text" : "their dog",
        "language_name" : "english",
        "language_id" : 38
      },
      "transliteration" : {
        "text" : "kalbuhum",
        "language_name" : "english",
        "language_id" : 38
      }
    }, {
      "id" : 24535,
      "position" : 5,
      "audio_url" : "wbw/018_022_005.mp3",
      "verse_key" : "18:22",
      "verse_id" : 2162,
      "location" : "18:22:5",
      "text_uthmani" : "وَيَقُولُونَ",
      "code_v1" : "ﭹ",
      "qpc_uthmani_hafs" : "وَيَقُولُونَ",
      "char_type_name" : "word",
      "page_number" : 296,
      "line_number" : 5,
      "text" : "ﭹ",
      "translation" : {
        "text" : "and they say",
        "language_name" : "english",
        "language_id" : 38
      },
      "transliteration" : {
        "text" : "wayaqūlūna",
        "language_name" : "english",
        "language_id" : 38
      }
    }, {
      "id" : 24536,
      "position" : 6,
      "audio_url" : "wbw/018_022_006.mp3",
      "verse_key" : "18:22",
      "verse_id" : 2162,
      "location" : "18:22:6",
      "text_uthmani" : "خَمْسَةٌۭ",
      "code_v1" : "ﭺ",
      "qpc_uthmani_hafs" : "خَمۡسَةٞ",
      "char_type_name" : "word",
      "page_number" : 296,
      "line_number" : 5,
      "text" : "ﭺ",
      "translation" : {
        "text" : "(they were) five",
        "language_name" : "english",
        "language_id" : 38
      },
      "transliteration" : {
        "text" : "khamsatun",
        "language_name" : "english",
        "language_id" : 38
      }
    }, {
      "id" : 24537,
      "position" : 7,
      "audio_url" : "wbw/018_022_007.mp3",
      "verse_key" : "18:22",
      "verse_id" : 2162,
      "location" : "18:22:7",
      "text_uthmani" : "سَادِسُهُمْ",
      "code_v1" : "ﭻ",
      "qpc_uthmani_hafs" : "سَادِسُهُمۡ",
      "char_type_name" : "word",
      "page_number" : 296,
      "line_number" : 5,
      "text" : "ﭻ",
      "translation" : {
        "text" : "the sixth of them",
        "language_name" : "english",
        "language_id" : 38
      },
      "transliteration" : {
        "text" : "sādisuhum",
        "language_name" : "english",
        "language_id" : 38
      }
    }, {
      "id" : 24538,
      "position" : 8,
      "audio_url" : "wbw/018_022_008.mp3",
      "verse_key" : "18:22",
      "verse_id" : 2162,
      "location" : "18:22:8",
      "text_uthmani" : "كَلْبُهُمْ",
      "code_v1" : "ﭼ",
      "qpc_uthmani_hafs" : "كَلۡبُهُمۡ",
      "char_type_name" : "word",
      "page_number" : 296,
      "line_number" : 5,
      "text" : "ﭼ",
      "translation" : {
        "text" : "their dog ",
        "language_name" : "english",
        "language_id" : 38
      },
      "transliteration" : {
        "text" : "kalbuhum",
        "language_name" : "english",
        "language_id" : 38
      }
    }, {
      "id" : 24539,
      "position" : 9,
      "audio_url" : "wbw/018_022_009.mp3",
      "verse_key" : "18:22",
      "verse_id" : 2162,
      "location" : "18:22:9",
      "text_uthmani" : "رَجْمًۢا",
      "code_v1" : "ﭽ",
      "qpc_uthmani_hafs" : "رَجۡمَۢا",
      "char_type_name" : "word",
      "page_number" : 296,
      "line_number" : 5,
      "text" : "ﭽ",
      "translation" : {
        "text" : "guessing",
        "language_name" : "english",
        "language_id" : 38
      },
      "transliteration" : {
        "text" : "rajman",
        "language_name" : "english",
        "language_id" : 38
      }
    }, {
      "id" : 24540,
      "position" : 10,
      "audio_url" : "wbw/018_022_010.mp3",
      "verse_key" : "18:22",
      "verse_id" : 2162,
      "location" : "18:22:10",
      "text_uthmani" : "بِٱلْغَيْبِ ۖ",
      "code_v1" : "ﭾﭿ",
      "qpc_uthmani_hafs" : "بِٱلۡغَيۡبِۖ",
      "char_type_name" : "word",
      "page_number" : 296,
      "line_number" : 6,
      "text" : "ﭾﭿ",
      "translation" : {
        "text" : "about the unseen",
        "language_name" : "english",
        "language_id" : 38
      },
      "transliteration" : {
        "text" : "bil-ghaybi",
        "language_name" : "english",
        "language_id" : 38
      }
    }, {
      "id" : 24542,
      "position" : 11,
      "audio_url" : "wbw/018_022_012.mp3",
      "verse_key" : "18:22",
      "verse_id" : 2162,
      "location" : "18:22:11",
      "text_uthmani" : "وَيَقُولُونَ",
      "code_v1" : "ﮀ",
      "qpc_uthmani_hafs" : "وَيَقُولُونَ",
      "char_type_name" : "word",
      "page_number" : 296,
      "line_number" : 6,
      "text" : "ﮀ",
      "translation" : {
        "text" : "and they say",
        "language_name" : "english",
        "language_id" : 38
      },
      "transliteration" : {
        "text" : "wayaqūlūna",
        "language_name" : "english",
        "language_id" : 38
      }
    }, {
      "id" : 24543,
      "position" : 12,
      "audio_url" : "wbw/018_022_013.mp3",
      "verse_key" : "18:22",
      "verse_id" : 2162,
      "location" : "18:22:12",
      "text_uthmani" : "سَبْعَةٌۭ",
      "code_v1" : "ﮁ",
      "qpc_uthmani_hafs" : "سَبۡعَةٞ",
      "char_type_name" : "word",
      "page_number" : 296,
      "line_number" : 6,
      "text" : "ﮁ",
      "translation" : {
        "text" : "(they were) seven",
        "language_name" : "english",
        "language_id" : 38
      },
      "transliteration" : {
        "text" : "sabʿatun",
        "language_name" : "english",
        "language_id" : 38
      }
    }, {
      "id" : 24544,
      "position" : 13,
      "audio_url" : "wbw/018_022_014.mp3",
      "verse_key" : "18:22",
      "verse_id" : 2162,
      "location" : "18:22:13",
      "text_uthmani" : "وَثَامِنُهُمْ",
      "code_v1" : "ﮂ",
      "qpc_uthmani_hafs" : "وَثَامِنُهُمۡ",
      "char_type_name" : "word",
      "page_number" : 296,
      "line_number" : 6,
      "text" : "ﮂ",
      "translation" : {
        "text" : "and the eight of them",
        "language_name" : "english",
        "language_id" : 38
      },
      "transliteration" : {
        "text" : "wathāminuhum",
        "language_name" : "english",
        "language_id" : 38
      }
    }, {
      "id" : 24545,
      "position" : 14,
      "audio_url" : "wbw/018_022_015.mp3",
      "verse_key" : "18:22",
      "verse_id" : 2162,
      "location" : "18:22:14",
      "text_uthmani" : "كَلْبُهُمْ ۚ",
      "code_v1" : "ﮃﮄ",
      "qpc_uthmani_hafs" : "كَلۡبُهُمۡۚ",
      "char_type_name" : "word",
      "page_number" : 296,
      "line_number" : 6,
      "text" : "ﮃﮄ",
      "translation" : {
        "text" : "their dog",
        "language_name" : "english",
        "language_id" : 38
      },
      "transliteration" : {
        "text" : "kalbuhum",
        "language_name" : "english",
        "language_id" : 38
      }
    }, {
      "id" : 24547,
      "position" : 15,
      "audio_url" : "wbw/018_022_017.mp3",
      "verse_key" : "18:22",
      "verse_id" : 2162,
      "location" : "18:22:15",
      "text_uthmani" : "قُل",
      "code_v1" : "ﮅ",
      "qpc_uthmani_hafs" : "قُل",
      "char_type_name" : "word",
      "page_number" : 296,
      "line_number" : 6,
      "text" : "ﮅ",
      "translation" : {
        "text" : "Say",
        "language_name" : "english",
        "language_id" : 38
      },
      "transliteration" : {
        "text" : "qul",
        "language_name" : "english",
        "language_id" : 38
      }
    }, {
      "id" : 24548,
      "position" : 16,
      "audio_url" : "wbw/018_022_018.mp3",
      "verse_key" : "18:22",
      "verse_id" : 2162,
      "location" : "18:22:16",
      "text_uthmani" : "رَّبِّىٓ",
      "code_v1" : "ﮆ",
      "qpc_uthmani_hafs" : "رَّبِّيٓ",
      "char_type_name" : "word",
      "page_number" : 296,
      "line_number" : 6,
      "text" : "ﮆ",
      "translation" : {
        "text" : "My Lord",
        "language_name" : "english",
        "language_id" : 38
      },
      "transliteration" : {
        "text" : "rabbī",
        "language_name" : "english",
        "language_id" : 38
      }
    }, {
      "id" : 24549,
      "position" : 17,
      "audio_url" : "wbw/018_022_019.mp3",
      "verse_key" : "18:22",
      "verse_id" : 2162,
      "location" : "18:22:17",
      "text_uthmani" : "أَعْلَمُ",
      "code_v1" : "ﮇ",
      "qpc_uthmani_hafs" : "أَعۡلَمُ",
      "char_type_name" : "word",
      "page_number" : 296,
      "line_number" : 6,
      "text" : "ﮇ",
      "translation" : {
        "text" : "knows best",
        "language_name" : "english",
        "language_id" : 38
      },
      "transliteration" : {
        "text" : "aʿlamu",
        "language_name" : "english",
        "language_id" : 38
      }
    }, {
      "id" : 24550,
      "position" : 18,
      "audio_url" : "wbw/018_022_020.mp3",
      "verse_key" : "18:22",
      "verse_id" : 2162,
      "location" : "18:22:18",
      "text_uthmani" : "بِعِدَّتِهِم",
      "code_v1" : "ﮈ",
      "qpc_uthmani_hafs" : "بِعِدَّتِهِم",
      "char_type_name" : "word",
      "page_number" : 296,
      "line_number" : 7,
      "text" : "ﮈ",
      "translation" : {
        "text" : "their number",
        "language_name" : "english",
        "language_id" : 38
      },
      "transliteration" : {
        "text" : "biʿiddatihim",
        "language_name" : "english",
        "language_id" : 38
      }
    }, {
      "id" : 24551,
      "position" : 19,
      "audio_url" : "wbw/018_022_021.mp3",
      "verse_key" : "18:22",
      "verse_id" : 2162,
      "location" : "18:22:19",
      "text_uthmani" : "مَّا",
      "code_v1" : "ﮉ",
      "qpc_uthmani_hafs" : "مَّا",
      "char_type_name" : "word",
      "page_number" : 296,
      "line_number" : 7,
      "text" : "ﮉ",
      "translation" : {
        "text" : "None",
        "language_name" : "english",
        "language_id" : 38
      },
      "transliteration" : {
        "text" : "mā",
        "language_name" : "english",
        "language_id" : 38
      }
    }, {
      "id" : 24552,
      "position" : 20,
      "audio_url" : "wbw/018_022_022.mp3",
      "verse_key" : "18:22",
      "verse_id" : 2162,
      "location" : "18:22:20",
      "text_uthmani" : "يَعْلَمُهُمْ",
      "code_v1" : "ﮊ",
      "qpc_uthmani_hafs" : "يَعۡلَمُهُمۡ",
      "char_type_name" : "word",
      "page_number" : 296,
      "line_number" : 7,
      "text" : "ﮊ",
      "translation" : {
        "text" : "knows them",
        "language_name" : "english",
        "language_id" : 38
      },
      "transliteration" : {
        "text" : "yaʿlamuhum",
        "language_name" : "english",
        "language_id" : 38
      }
    }, {
      "id" : 24553,
      "position" : 21,
      "audio_url" : "wbw/018_022_023.mp3",
      "verse_key" : "18:22",
      "verse_id" : 2162,
      "location" : "18:22:21",
      "text_uthmani" : "إِلَّا",
      "code_v1" : "ﮋ",
      "qpc_uthmani_hafs" : "إِلَّا",
      "char_type_name" : "word",
      "page_number" : 296,
      "line_number" : 7,
      "text" : "ﮋ",
      "translation" : {
        "text" : "except",
        "language_name" : "english",
        "language_id" : 38
      },
      "transliteration" : {
        "text" : "illā",
        "language_name" : "english",
        "language_id" : 38
      }
    }, {
      "id" : 24554,
      "position" : 22,
      "audio_url" : "wbw/018_022_024.mp3",
      "verse_key" : "18:22",
      "verse_id" : 2162,
      "location" : "18:22:22",
      "text_uthmani" : "قَلِيلٌۭ ۗ",
      "code_v1" : "ﮌﮍ",
      "qpc_uthmani_hafs" : "قَلِيلٞۗ",
      "char_type_name" : "word",
      "page_number" : 296,
      "line_number" : 7,
      "text" : "ﮌﮍ",
      "translation" : {
        "text" : "a few",
        "language_name" : "english",
        "language_id" : 38
      },
      "transliteration" : {
        "text" : "qalīlun",
        "language_name" : "english",
        "language_id" : 38
      }
    }, {
      "id" : 24556,
      "position" : 23,
      "audio_url" : "wbw/018_022_026.mp3",
      "verse_key" : "18:22",
      "verse_id" : 2162,
      "location" : "18:22:23",
      "text_uthmani" : "فَلَا",
      "code_v1" : "ﮎ",
      "qpc_uthmani_hafs" : "فَلَا",
      "char_type_name" : "word",
      "page_number" : 296,
      "line_number" : 7,
      "text" : "ﮎ",
      "translation" : {
        "text" : "So (do) not",
        "language_name" : "english",
        "language_id" : 38
      },
      "transliteration" : {
        "text" : "falā",
        "language_name" : "english",
        "language_id" : 38
      }
    }, {
      "id" : 24557,
      "position" : 24,
      "audio_url" : "wbw/018_022_027.mp3",
      "verse_key" : "18:22",
      "verse_id" : 2162,
      "location" : "18:22:24",
      "text_uthmani" : "تُمَارِ",
      "code_v1" : "ﮏ",
      "qpc_uthmani_hafs" : "تُمَارِ",
      "char_type_name" : "word",
      "page_number" : 296,
      "line_number" : 7,
      "text" : "ﮏ",
      "translation" : {
        "text" : "argue",
        "language_name" : "english",
        "language_id" : 38
      },
      "transliteration" : {
        "text" : "tumāri",
        "language_name" : "english",
        "language_id" : 38
      }
    }, {
      "id" : 24558,
      "position" : 25,
      "audio_url" : "wbw/018_022_028.mp3",
      "verse_key" : "18:22",
      "verse_id" : 2162,
      "location" : "18:22:25",
      "text_uthmani" : "فِيهِمْ",
      "code_v1" : "ﮐ",
      "qpc_uthmani_hafs" : "فِيهِمۡ",
      "char_type_name" : "word",
      "page_number" : 296,
      "line_number" : 7,
      "text" : "ﮐ",
      "translation" : {
        "text" : "about them",
        "language_name" : "english",
        "language_id" : 38
      },
      "transliteration" : {
        "text" : "fīhim",
        "language_name" : "english",
        "language_id" : 38
      }
    }, {
      "id" : 24559,
      "position" : 26,
      "audio_url" : "wbw/018_022_029.mp3",
      "verse_key" : "18:22",
      "verse_id" : 2162,
      "location" : "18:22:26",
      "text_uthmani" : "إِلَّا",
      "code_v1" : "ﮑ",
      "qpc_uthmani_hafs" : "إِلَّا",
      "char_type_name" : "word",
      "page_number" : 296,
      "line_number" : 7,
      "text" : "ﮑ",
      "translation" : {
        "text" : "except",
        "language_name" : "english",
        "language_id" : 38
      },
      "transliteration" : {
        "text" : "illā",
        "language_name" : "english",
        "language_id" : 38
      }
    }, {
      "id" : 24560,
      "position" : 27,
      "audio_url" : "wbw/018_022_030.mp3",
      "verse_key" : "18:22",
      "verse_id" : 2162,
      "location" : "18:22:27",
      "text_uthmani" : "مِرَآءًۭ",
      "code_v1" : "ﮒ",
      "qpc_uthmani_hafs" : "مِرَآءٗ",
      "char_type_name" : "word",
      "page_number" : 296,
      "line_number" : 7,
      "text" : "ﮒ",
      "translation" : {
        "text" : "(with) an argument",
        "language_name" : "english",
        "language_id" : 38
      },
      "transliteration" : {
        "text" : "mirāan",
        "language_name" : "english",
        "language_id" : 38
      }
    }, {
      "id" : 24561,
      "position" : 28,
      "audio_url" : "wbw/018_022_031.mp3",
      "verse_key" : "18:22",
      "verse_id" : 2162,
      "location" : "18:22:28",
      "text_uthmani" : "ظَـٰهِرًۭا",
      "code_v1" : "ﮓ",
      "qpc_uthmani_hafs" : "ظَٰهِرٗا",
      "char_type_name" : "word",
      "page_number" : 296,
      "line_number" : 7,
      "text" : "ﮓ",
      "translation" : {
        "text" : "obvious",
        "language_name" : "english",
        "language_id" : 38
      },
      "transliteration" : {
        "text" : "ẓāhiran",
        "language_name" : "english",
        "language_id" : 38
      }
    }, {
      "id" : 24562,
      "position" : 29,
      "audio_url" : "wbw/018_022_032.mp3",
      "verse_key" : "18:22",
      "verse_id" : 2162,
      "location" : "18:22:29",
      "text_uthmani" : "وَلَا",
      "code_v1" : "ﮔ",
      "qpc_uthmani_hafs" : "وَلَا",
      "char_type_name" : "word",
      "page_number" : 296,
      "line_number" : 8,
      "text" : "ﮔ",
      "translation" : {
        "text" : "and (do) not",
        "language_name" : "english",
        "language_id" : 38
      },
      "transliteration" : {
        "text" : "walā",
        "language_name" : "english",
        "language_id" : 38
      }
    }, {
      "id" : 24563,
      "position" : 30,
      "audio_url" : "wbw/018_022_033.mp3",
      "verse_key" : "18:22",
      "verse_id" : 2162,
      "location" : "18:22:30",
      "text_uthmani" : "تَسْتَفْتِ",
      "code_v1" : "ﮕ",
      "qpc_uthmani_hafs" : "تَسۡتَفۡتِ",
      "char_type_name" : "word",
      "page_number" : 296,
      "line_number" : 8,
      "text" : "ﮕ",
      "translation" : {
        "text" : "inquire",
        "language_name" : "english",
        "language_id" : 38
      },
      "transliteration" : {
        "text" : "tastafti",
        "language_name" : "english",
        "language_id" : 38
      }
    }, {
      "id" : 24564,
      "position" : 31,
      "audio_url" : "wbw/018_022_034.mp3",
      "verse_key" : "18:22",
      "verse_id" : 2162,
      "location" : "18:22:31",
      "text_uthmani" : "فِيهِم",
      "code_v1" : "ﮖ",
      "qpc_uthmani_hafs" : "فِيهِم",
      "char_type_name" : "word",
      "page_number" : 296,
      "line_number" : 8,
      "text" : "ﮖ",
      "translation" : {
        "text" : "about them",
        "language_name" : "english",
        "language_id" : 38
      },
      "transliteration" : {
        "text" : "fīhim",
        "language_name" : "english",
        "language_id" : 38
      }
    }, {
      "id" : 24565,
      "position" : 32,
      "audio_url" : "wbw/018_022_035.mp3",
      "verse_key" : "18:22",
      "verse_id" : 2162,
      "location" : "18:22:32",
      "text_uthmani" : "مِّنْهُمْ",
      "code_v1" : "ﮗ",
      "qpc_uthmani_hafs" : "مِّنۡهُمۡ",
      "char_type_name" : "word",
      "page_number" : 296,
      "line_number" : 8,
      "text" : "ﮗ",
      "translation" : {
        "text" : "among them",
        "language_name" : "english",
        "language_id" : 38
      },
      "transliteration" : {
        "text" : "min'hum",
        "language_name" : "english",
        "language_id" : 38
      }
    }, {
      "id" : 24566,
      "position" : 33,
      "audio_url" : "wbw/018_022_036.mp3",
      "verse_key" : "18:22",
      "verse_id" : 2162,
      "location" : "18:22:33",
      "text_uthmani" : "أَحَدًۭا",
      "code_v1" : "ﮘ",
      "qpc_uthmani_hafs" : "أَحَدٗا",
      "char_type_name" : "word",
      "page_number" : 296,
      "line_number" : 8,
      "text" : "ﮘ",
      "translation" : {
        "text" : "(from) anyone",
        "language_name" : "english",
        "language_id" : 38
      },
      "transliteration" : {
        "text" : "aḥadan",
        "language_name" : "english",
        "language_id" : 38
      }
    }, {
      "id" : 24567,
      "position" : 34,
      "audio_url" : null,
      "verse_key" : "18:22",
      "verse_id" : 2162,
      "location" : "18:22:34",
      "text_uthmani" : "٢٢",
      "code_v1" : "ﮙ",
      "qpc_uthmani_hafs" : "٢٢",
      "char_type_name" : "end",
      "page_number" : 296,
      "line_number" : 8,
      "text" : "ﮙ",
      "translation" : {
        "text" : "(22)",
        "language_name" : "english",
        "language_id" : 38
      },
      "transliteration" : {
        "text" : null,
        "language_name" : "english",
        "language_id" : 38
      }
    } ]
  }, {
    "id" : 2163,
    "verse_number" : 23,
    "verse_key" : "18:23",
    "hizb_number" : 30,
    "rub_el_hizb_number" : 118,
    "ruku_number" : 255,
    "manzil_number" : 4,
    "sajdah_number" : null,
    "text_uthmani" : "وَلَا تَقُولَنَّ لِشَا۟ىْءٍ إِنِّى فَاعِلٌ ذَٰلِكَ غَدًا",
    "chapter_id" : 18,
    "text_imlaei_simple" : "ولا تقولن لشيء اني فاعل ذلك غدا",
    "page_number" : 296,
    "juz_number" : 15,
    "words" : [ {
      "id" : 25631,
      "position" : 1,
      "audio_url" : "wbw/018_023_001.mp3",
      "verse_key" : "18:23",
      "verse_id" : 2163,
      "location" : "18:23:1",
      "text_uthmani" : "وَلَا",
      "code_v1" : "ﮚ",
      "qpc_uthmani_hafs" : "وَلَا",
      "char_type_name" : "word",
      "page_number" : 296,
      "line_number" : 8,
      "text" : "ﮚ",
      "translation" : {
        "text" : "And (do) not",
        "language_name" : "english",
        "language_id" : 38
      },
      "transliteration" : {
        "text" : "walā",
        "language_name" : "english",
        "language_id" : 38
      }
    }, {
      "id" : 25632,
      "position" : 2,
      "audio_url" : "wbw/018_023_002.mp3",
      "verse_key" : "18:23",
      "verse_id" : 2163,
      "location" : "18:23:2",
      "text_uthmani" : "تَقُولَنَّ",
      "code_v1" : "ﮛ",
      "qpc_uthmani_hafs" : "تَقُولَنَّ",
      "char_type_name" : "word",
      "page_number" : 296,
      "line_number" : 8,
      "text" : "ﮛ",
      "translation" : {
        "text" : "say",
        "language_name" : "english",
        "language_id" : 38
      },
      "transliteration" : {
        "text" : "taqūlanna",
        "language_name" : "english",
        "language_id" : 38
      }
    }, {
      "id" : 25633,
      "position" : 3,
      "audio_url" : "wbw/018_023_003.mp3",
      "verse_key" : "18:23",
      "verse_id" : 2163,
      "location" : "18:23:3",
      "text_uthmani" : "لِشَا۟ىْءٍ",
      "code_v1" : "ﮜ",
      "qpc_uthmani_hafs" : "لِشَاْيۡءٍ",
      "char_type_name" : "word",
      "page_number" : 296,
      "line_number" : 8,
      "text" : "ﮜ",
      "translation" : {
        "text" : "of anything",
        "language_name" : "english",
        "language_id" : 38
      },
      "transliteration" : {
        "text" : "lishāy'in",
        "language_name" : "english",
        "language_id" : 38
      }
    }, {
      "id" : 25634,
      "position" : 4,
      "audio_url" : "wbw/018_023_004.mp3",
      "verse_key" : "18:23",
      "verse_id" : 2163,
      "location" : "18:23:4",
      "text_uthmani" : "إِنِّى",
      "code_v1" : "ﮝ",
      "qpc_uthmani_hafs" : "إِنِّي",
      "char_type_name" : "word",
      "page_number" : 296,
      "line_number" : 9,
      "text" : "ﮝ",
      "translation" : {
        "text" : "Indeed, I",
        "language_name" : "english",
        "language_id" : 38
      },
      "transliteration" : {
        "text" : "innī",
        "language_name" : "english",
        "language_id" : 38
      }
    }, {
      "id" : 25635,
      "position" : 5,
      "audio_url" : "wbw/018_023_005.mp3",
      "verse_key" : "18:23",
      "verse_id" : 2163,
      "location" : "18:23:5",
      "text_uthmani" : "فَاعِلٌۭ",
      "code_v1" : "ﮞ",
      "qpc_uthmani_hafs" : "فَاعِلٞ",
      "char_type_name" : "word",
      "page_number" : 296,
      "line_number" : 9,
      "text" : "ﮞ",
      "translation" : {
        "text" : "will do",
        "language_name" : "english",
        "language_id" : 38
      },
      "transliteration" : {
        "text" : "fāʿilun",
        "language_name" : "english",
        "language_id" : 38
      }
    }, {
      "id" : 25636,
      "position" : 6,
      "audio_url" : "wbw/018_023_006.mp3",
      "verse_key" : "18:23",
      "verse_id" : 2163,
      "location" : "18:23:6",
      "text_uthmani" : "ذَٰلِكَ",
      "code_v1" : "ﮟ",
      "qpc_uthmani_hafs" : "ذَٰلِكَ",
      "char_type_name" : "word",
      "page_number" : 296,
      "line_number" : 9,
      "text" : "ﮟ",
      "translation" : {
        "text" : "that",
        "language_name" : "english",
        "language_id" : 38
      },
      "transliteration" : {
        "text" : "dhālika",
        "language_name" : "english",
        "language_id" : 38
      }
    }, {
      "id" : 25637,
      "position" : 7,
      "audio_url" : "wbw/018_023_007.mp3",
      "verse_key" : "18:23",
      "verse_id" : 2163,
      "location" : "18:23:7",
      "text_uthmani" : "غَدًا",
      "code_v1" : "ﮠ",
      "qpc_uthmani_hafs" : "غَدًا",
      "char_type_name" : "word",
      "page_number" : 296,
      "line_number" : 9,
      "text" : "ﮠ",
      "translation" : {
        "text" : "tomorrow",
        "language_name" : "english",
        "language_id" : 38
      },
      "transliteration" : {
        "text" : "ghadan",
        "language_name" : "english",
        "language_id" : 38
      }
    }, {
      "id" : 25638,
      "position" : 8,
      "audio_url" : null,
      "verse_key" : "18:23",
      "verse_id" : 2163,
      "location" : "18:23:8",
      "text_uthmani" : "٢٣",
      "code_v1" : "ﮡ",
      "qpc_uthmani_hafs" : "٢٣",
      "char_type_name" : "end",
      "page_number" : 296,
      "line_number" : 9,
      "text" : "ﮡ",
      "translation" : {
        "text" : "(23)",
        "language_name" : "english",
        "language_id" : 38
      },
      "transliteration" : {
        "text" : null,
        "language_name" : "english",
        "language_id" : 38
      }
    } ]
  }, {
    "id" : 2164,
    "verse_number" : 24,
    "verse_key" : "18:24",
    "hizb_number" : 30,
    "rub_el_hizb_number" : 118,
    "ruku_number" : 255,
    "manzil_number" : 4,
    "sajdah_number" : null,
    "text_uthmani" : "إِلَّآ أَن يَشَآءَ ٱللَّهُ ۚ وَٱذْكُر رَّبَّكَ إِذَا نَسِيتَ وَقُلْ عَسَىٰٓ أَن يَهْدِيَنِ رَبِّى لِأَقْرَبَ مِنْ هَـٰذَا رَشَدًا",
    "chapter_id" : 18,
    "text_imlaei_simple" : "الا ان يشاء الله واذكر ربك اذا نسيت وقل عسى ان يهدين ربي لاقرب من هذا رشدا",
    "page_number" : 296,
    "juz_number" : 15,
    "words" : [ {
      "id" : 26689,
      "position" : 1,
      "audio_url" : "wbw/018_024_001.mp3",
      "verse_key" : "18:24",
      "verse_id" : 2164,
      "location" : "18:24:1",
      "text_uthmani" : "إِلَّآ",
      "code_v1" : "ﮢ",
      "qpc_uthmani_hafs" : "إِلَّآ",
      "char_type_name" : "word",
      "page_number" : 296,
      "line_number" : 9,
      "text" : "ﮢ",
      "translation" : {
        "text" : "Except",
        "language_name" : "english",
        "language_id" : 38
      },
      "transliteration" : {
        "text" : "illā",
        "language_name" : "english",
        "language_id" : 38
      }
    }, {
      "id" : 26690,
      "position" : 2,
      "audio_url" : "wbw/018_024_002.mp3",
      "verse_key" : "18:24",
      "verse_id" : 2164,
      "location" : "18:24:2",
      "text_uthmani" : "أَن",
      "code_v1" : "ﮣ",
      "qpc_uthmani_hafs" : "أَن",
      "char_type_name" : "word",
      "page_number" : 296,
      "line_number" : 9,
      "text" : "ﮣ",
      "translation" : {
        "text" : "If",
        "language_name" : "english",
        "language_id" : 38
      },
      "transliteration" : {
        "text" : "an",
        "language_name" : "english",
        "language_id" : 38
      }
    }, {
      "id" : 26691,
      "position" : 3,
      "audio_url" : "wbw/018_024_003.mp3",
      "verse_key" : "18:24",
      "verse_id" : 2164,
      "location" : "18:24:3",
      "text_uthmani" : "يَشَآءَ",
      "code_v1" : "ﮤ",
      "qpc_uthmani_hafs" : "يَشَآءَ",
      "char_type_name" : "word",
      "page_number" : 296,
      "line_number" : 9,
      "text" : "ﮤ",
      "translation" : {
        "text" : "Allah wills",
        "language_name" : "english",
        "language_id" : 38
      },
      "transliteration" : {
        "text" : "yashāa",
        "language_name" : "english",
        "language_id" : 38
      }
    }, {
      "id" : 26692,
      "position" : 4,
      "audio_url" : "wbw/018_024_004.mp3",
      "verse_key" : "18:24",
      "verse_id" : 2164,
      "location" : "18:24:4",
      "text_uthmani" : "ٱللَّهُ ۚ",
      "code_v1" : "ﮥﮦ",
      "qpc_uthmani_hafs" : "ٱللَّهُۚ",
      "char_type_name" : "word",
      "page_number" : 296,
      "line_number" : 9,
      "text" : "ﮥﮦ",
      "translation" : {
        "text" : "Allah wills",
        "language_name" : "english",
        "language_id" : 38
      },
      "transliteration" : {
        "text" : "l-lahu",
        "language_name" : "english",
        "language_id" : 38
      }
    }, {
      "id" : 26694,
      "position" : 5,
      "audio_url" : "wbw/018_024_006.mp3",
      "verse_key" : "18:24",
      "verse_id" : 2164,
      "location" : "18:24:5",
      "text_uthmani" : "وَٱذْكُر",
      "code_v1" : "ﮧ",
      "qpc_uthmani_hafs" : "وَٱذۡكُر",
      "char_type_name" : "word",
      "page_number" : 296,
      "line_number" : 9,
      "text" : "ﮧ",
      "translation" : {
        "text" : "And remember",
        "language_name" : "english",
        "language_id" : 38
      },
      "transliteration" : {
        "text" : "wa-udh'kur",
        "language_name" : "english",
        "language_id" : 38
      }
    }, {
      "id" : 26695,
      "position" : 6,
      "audio_url" : "wbw/018_024_007.mp3",
      "verse_key" : "18:24",
      "verse_id" : 2164,
      "location" : "18:24:6",
      "text_uthmani" : "رَّبَّكَ",
      "code_v1" : "ﮨ",
      "qpc_uthmani_hafs" : "رَّبَّكَ",
      "char_type_name" : "word",
      "page_number" : 296,
      "line_number" : 9,
      "text" : "ﮨ",
      "translation" : {
        "text" : "your Lord",
        "language_name" : "english",
        "language_id" : 38
      },
      "transliteration" : {
        "text" : "rabbaka",
        "language_name" : "english",
        "language_id" : 38
      }
    }, {
      "id" : 26696,
      "position" : 7,
      "audio_url" : "wbw/018_024_008.mp3",
      "verse_key" : "18:24",
      "verse_id" : 2164,
      "location" : "18:24:7",
      "text_uthmani" : "إِذَا",
      "code_v1" : "ﮩ",
      "qpc_uthmani_hafs" : "إِذَا",
      "char_type_name" : "word",
      "page_number" : 296,
      "line_number" : 10,
      "text" : "ﮩ",
      "translation" : {
        "text" : "when",
        "language_name" : "english",
        "language_id" : 38
      },
      "transliteration" : {
        "text" : "idhā",
        "language_name" : "english",
        "language_id" : 38
      }
    }, {
      "id" : 26697,
      "position" : 8,
      "audio_url" : "wbw/018_024_009.mp3",
      "verse_key" : "18:24",
      "verse_id" : 2164,
      "location" : "18:24:8",
      "text_uthmani" : "نَسِيتَ",
      "code_v1" : "ﮪ",
      "qpc_uthmani_hafs" : "نَسِيتَ",
      "char_type_name" : "word",
      "page_number" : 296,
      "line_number" : 10,
      "text" : "ﮪ",
      "translation" : {
        "text" : "you forget",
        "language_name" : "english",
        "language_id" : 38
      },
      "transliteration" : {
        "text" : "nasīta",
        "language_name" : "english",
        "language_id" : 38
      }
    }, {
      "id" : 26698,
      "position" : 9,
      "audio_url" : "wbw/018_024_010.mp3",
      "verse_key" : "18:24",
      "verse_id" : 2164,
      "location" : "18:24:9",
      "text_uthmani" : "وَقُلْ",
      "code_v1" : "ﮫ",
      "qpc_uthmani_hafs" : "وَقُلۡ",
      "char_type_name" : "word",
      "page_number" : 296,
      "line_number" : 10,
      "text" : "ﮫ",
      "translation" : {
        "text" : "and say",
        "language_name" : "english",
        "language_id" : 38
      },
      "transliteration" : {
        "text" : "waqul",
        "language_name" : "english",
        "language_id" : 38
      }
    }, {
      "id" : 26699,
      "position" : 10,
      "audio_url" : "wbw/018_024_011.mp3",
      "verse_key" : "18:24",
      "verse_id" : 2164,
      "location" : "18:24:10",
      "text_uthmani" : "عَسَىٰٓ",
      "code_v1" : "ﮬ",
      "qpc_uthmani_hafs" : "عَسَىٰٓ",
      "char_type_name" : "word",
      "page_number" : 296,
      "line_number" : 10,
      "text" : "ﮬ",
      "translation" : {
        "text" : "Perhaps",
        "language_name" : "english",
        "language_id" : 38
      },
      "transliteration" : {
        "text" : "ʿasā",
        "language_name" : "english",
        "language_id" : 38
      }
    }, {
      "id" : 26700,
      "position" : 11,
      "audio_url" : "wbw/018_024_012.mp3",
      "verse_key" : "18:24",
      "verse_id" : 2164,
      "location" : "18:24:11",
      "text_uthmani" : "أَن",
      "code_v1" : "ﮭ",
      "qpc_uthmani_hafs" : "أَن",
      "char_type_name" : "word",
      "page_number" : 296,
      "line_number" : 10,
      "text" : "ﮭ",
      "translation" : {
        "text" : "[that]",
        "language_name" : "english",
        "language_id" : 38
      },
      "transliteration" : {
        "text" : "an",
        "language_name" : "english",
        "language_id" : 38
      }
    }, {
      "id" : 26701,
      "position" : 12,
      "audio_url" : "wbw/018_024_013.mp3",
      "verse_key" : "18:24",
      "verse_id" : 2164,
      "location" : "18:24:12",
      "text_uthmani" : "يَهْدِيَنِ",
      "code_v1" : "ﮮ",
      "qpc_uthmani_hafs" : "يَهۡدِيَنِ",
      "char_type_name" : "word",
      "page_number" : 296,
      "line_number" : 10,
      "text" : "ﮮ",
      "translation" : {
        "text" : "will guide me",
        "language_name" : "english",
        "language_id" : 38
      },
      "transliteration" : {
        "text" : "yahdiyani",
        "language_name" : "english",
        "language_id" : 38
      }
    }, {
      "id" : 26702,
      "position" : 13,
      "audio_url" : "wbw/018_024_014.mp3",
      "verse_key" : "18:24",
      "verse_id" : 2164,
      "location" : "18:24:13",
      "text_uthmani" : "رَبِّى",
      "code_v1" : "ﮯ",
      "qpc_uthmani_hafs" : "رَبِّي",
      "char_type_name" : "word",
      "page_number" : 296,
      "line_number" : 10,
      "text" : "ﮯ",
      "translation" : {
        "text" : "my Lord",
        "language_name" : "english",
        "language_id" : 38
      },
      "transliteration" : {
        "text" : "rabbī",
        "language_name" : "english",
        "language_id" : 38
      }
    }, {
      "id" : 26703,
      "position" : 14,
      "audio_url" : "wbw/018_024_015.mp3",
      "verse_key" : "18:24",
      "verse_id" : 2164,
      "location" : "18:24:14",
      "text_uthmani" : "لِأَقْرَبَ",
      "code_v1" : "ﮰ",
      "qpc_uthmani_hafs" : "لِأَقۡرَبَ",
      "char_type_name" : "word",
      "page_number" : 296,
      "line_number" : 10,
      "text" : "ﮰ",
      "translation" : {
        "text" : "to a nearer (way)",
        "language_name" : "english",
        "language_id" : 38
      },
      "transliteration" : {
        "text" : "li-aqraba",
        "language_name" : "english",
        "language_id" : 38
      }
    }, {
      "id" : 26704,
      "position" : 15,
      "audio_url" : "wbw/018_024_016.mp3",
      "verse_key" : "18:24",
      "verse_id" : 2164,
      "location" : "18:24:15",
      "text_uthmani" : "مِنْ",
      "code_v1" : "ﮱ",
      "qpc_uthmani_hafs" : "مِنۡ",
      "char_type_name" : "word",
      "page_number" : 296,
      "line_number" : 10,
      "text" : "ﮱ",
      "translation" : {
        "text" : "than",
        "language_name" : "english",
        "language_id" : 38
      },
      "transliteration" : {
        "text" : "min",
        "language_name" : "english",
        "language_id" : 38
      }
    }, {
      "id" : 26705,
      "position" : 16,
      "audio_url" : "wbw/018_024_017.mp3",
      "verse_key" : "18:24",
      "verse_id" : 2164,
      "location" : "18:24:16",
      "text_uthmani" : "هَـٰذَا",
      "code_v1" : "ﯓ",
      "qpc_uthmani_hafs" : "هَٰذَا",
      "char_type_name" : "word",
      "page_number" : 296,
      "line_number" : 10,
      "text" : "ﯓ",
      "translation" : {
        "text" : "this",
        "language_name" : "english",
        "language_id" : 38
      },
      "transliteration" : {
        "text" : "hādhā",
        "language_name" : "english",
        "language_id" : 38
      }
    }, {
      "id" : 26706,
      "position" : 17,
      "audio_url" : "wbw/018_024_018.mp3",
      "verse_key" : "18:24",
      "verse_id" : 2164,
      "location" : "18:24:17",
      "text_uthmani" : "رَشَدًۭا",
      "code_v1" : "ﯔ",
      "qpc_uthmani_hafs" : "رَشَدٗا",
      "char_type_name" : "word",
      "page_number" : 296,
      "line_number" : 10,
      "text" : "ﯔ",
      "translation" : {
        "text" : "right way",
        "language_name" : "english",
        "language_id" : 38
      },
      "transliteration" : {
        "text" : "rashadan",
        "language_name" : "english",
        "language_id" : 38
      }
    }, {
      "id" : 26707,
      "position" : 18,
      "audio_url" : null,
      "verse_key" : "18:24",
      "verse_id" : 2164,
      "location" : "18:24:18",
      "text_uthmani" : "٢٤",
      "code_v1" : "ﯕ",
      "qpc_uthmani_hafs" : "٢٤",
      "char_type_name" : "end",
      "page_number" : 296,
      "line_number" : 11,
      "text" : "ﯕ",
      "translation" : {
        "text" : "(24)",
        "language_name" : "english",
        "language_id" : 38
      },
      "transliteration" : {
        "text" : null,
        "language_name" : "english",
        "language_id" : 38
      }
    } ]
  }, {
    "id" : 2165,
    "verse_number" : 25,
    "verse_key" : "18:25",
    "hizb_number" : 30,
    "rub_el_hizb_number" : 118,
    "ruku_number" : 255,
    "manzil_number" : 4,
    "sajdah_number" : null,
    "text_uthmani" : "وَلَبِثُوا۟ فِى كَهْفِهِمْ ثَلَـٰثَ مِا۟ئَةٍ سِنِينَ وَٱزْدَادُوا۟ تِسْعًا",
    "chapter_id" : 18,
    "text_imlaei_simple" : "ولبثوا في كهفهم ثلاث مائة سنين وازدادوا تسعا",
    "page_number" : 296,
    "juz_number" : 15,
    "words" : [ {
      "id" : 27705,
      "position" : 1,
      "audio_url" : "wbw/018_025_001.mp3",
      "verse_key" : "18:25",
      "verse_id" : 2165,
      "location" : "18:25:1",
      "text_uthmani" : "وَلَبِثُوا۟",
      "code_v1" : "ﯖ",
      "qpc_uthmani_hafs" : "وَلَبِثُواْ",
      "char_type_name" : "word",
      "page_number" : 296,
      "line_number" : 11,
      "text" : "ﯖ",
      "translation" : {
        "text" : "And they remained",
        "language_name" : "english",
        "language_id" : 38
      },
      "transliteration" : {
        "text" : "walabithū",
        "language_name" : "english",
        "language_id" : 38
      }
    }, {
      "id" : 27706,
      "position" : 2,
      "audio_url" : "wbw/018_025_002.mp3",
      "verse_key" : "18:25",
      "verse_id" : 2165,
      "location" : "18:25:2",
      "text_uthmani" : "فِى",
      "code_v1" : "ﯗ",
      "qpc_uthmani_hafs" : "فِي",
      "char_type_name" : "word",
      "page_number" : 296,
      "line_number" : 11,
      "text" : "ﯗ",
      "translation" : {
        "text" : "in",
        "language_name" : "english",
        "language_id" : 38
      },
      "transliteration" : {
        "text" : "fī",
        "language_name" : "english",
        "language_id" : 38
      }
    }, {
      "id" : 27707,
      "position" : 3,
      "audio_url" : "wbw/018_025_003.mp3",
      "verse_key" : "18:25",
      "verse_id" : 2165,
      "location" : "18:25:3",
      "text_uthmani" : "كَهْفِهِمْ",
      "code_v1" : "ﯘ",
      "qpc_uthmani_hafs" : "كَهۡفِهِمۡ",
      "char_type_name" : "word",
      "page_number" : 296,
      "line_number" : 11,
      "text" : "ﯘ",
      "translation" : {
        "text" : "their cave",
        "language_name" : "english",
        "language_id" : 38
      },
      "transliteration" : {
        "text" : "kahfihim",
        "language_name" : "english",
        "language_id" : 38
      }
    }, {
      "id" : 27708,
      "position" : 4,
      "audio_url" : "wbw/018_025_004.mp3",
      "verse_key" : "18:25",
      "verse_id" : 2165,
      "location" : "18:25:4",
      "text_uthmani" : "ثَلَـٰثَ",
      "code_v1" : "ﯙ",
      "qpc_uthmani_hafs" : "ثَلَٰثَ",
      "char_type_name" : "word",
      "page_number" : 296,
      "line_number" : 11,
      "text" : "ﯙ",
      "translation" : {
        "text" : "(for) three",
        "language_name" : "english",
        "language_id" : 38
      },
      "transliteration" : {
        "text" : "thalātha",
        "language_name" : "english",
        "language_id" : 38
      }
    }, {
      "id" : 27709,
      "position" : 5,
      "audio_url" : "wbw/018_025_005.mp3",
      "verse_key" : "18:25",
      "verse_id" : 2165,
      "location" : "18:25:5",
      "text_uthmani" : "مِا۟ئَةٍۢ",
      "code_v1" : "ﯚ",
      "qpc_uthmani_hafs" : "مِاْئَةٖ",
      "char_type_name" : "word",
      "page_number" : 296,
      "line_number" : 11,
      "text" : "ﯚ",
      "translation" : {
        "text" : "hundred",
        "language_name" : "english",
        "language_id" : 38
      },
      "transliteration" : {
        "text" : "mi-atin",
        "language_name" : "english",
        "language_id" : 38
      }
    }, {
      "id" : 27710,
      "position" : 6,
      "audio_url" : "wbw/018_025_006.mp3",
      "verse_key" : "18:25",
      "verse_id" : 2165,
      "location" : "18:25:6",
      "text_uthmani" : "سِنِينَ",
      "code_v1" : "ﯛ",
      "qpc_uthmani_hafs" : "سِنِينَ",
      "char_type_name" : "word",
      "page_number" : 296,
      "line_number" : 11,
      "text" : "ﯛ",
      "translation" : {
        "text" : "years",
        "language_name" : "english",
        "language_id" : 38
      },
      "transliteration" : {
        "text" : "sinīna",
        "language_name" : "english",
        "language_id" : 38
      }
    }, {
      "id" : 27711,
      "position" : 7,
      "audio_url" : "wbw/018_025_007.mp3",
      "verse_key" : "18:25",
      "verse_id" : 2165,
      "location" : "18:25:7",
      "text_uthmani" : "وَٱزْدَادُوا۟",
      "code_v1" : "ﯜ",
      "qpc_uthmani_hafs" : "وَٱزۡدَادُواْ",
      "char_type_name" : "word",
      "page_number" : 296,
      "line_number" : 11,
      "text" : "ﯜ",
      "translation" : {
        "text" : "and add",
        "language_name" : "english",
        "language_id" : 38
      },
      "transliteration" : {
        "text" : "wa-iz'dādū",
        "language_name" : "english",
        "language_id" : 38
      }
    }, {
      "id" : 27712,
      "position" : 8,
      "audio_url" : "wbw/018_025_008.mp3",
      "verse_key" : "18:25",
      "verse_id" : 2165,
      "location" : "18:25:8",
      "text_uthmani" : "تِسْعًۭا",
      "code_v1" : "ﯝ",
      "qpc_uthmani_hafs" : "تِسۡعٗا",
      "char_type_name" : "word",
      "page_number" : 296,
      "line_number" : 11,
      "text" : "ﯝ",
      "translation" : {
        "text" : "nine",
        "language_name" : "english",
        "language_id" : 38
      },
      "transliteration" : {
        "text" : "tis'ʿan",
        "language_name" : "english",
        "language_id" : 38
      }
    }, {
      "id" : 27713,
      "position" : 9,
      "audio_url" : null,
      "verse_key" : "18:25",
      "verse_id" : 2165,
      "location" : "18:25:9",
      "text_uthmani" : "٢٥",
      "code_v1" : "ﯞ",
      "qpc_uthmani_hafs" : "٢٥",
      "char_type_name" : "end",
      "page_number" : 296,
      "line_number" : 12,
      "text" : "ﯞ",
      "translation" : {
        "text" : "(25)",
        "language_name" : "english",
        "language_id" : 38
      },
      "transliteration" : {
        "text" : null,
        "language_name" : "english",
        "language_id" : 38
      }
    } ]
  }, {
    "id" : 2166,
    "verse_number" : 26,
    "verse_key" : "18:26",
    "hizb_number" : 30,
    "rub_el_hizb_number" : 118,
    "ruku_number" : 255,
    "manzil_number" : 4,
    "sajdah_number" : null,
    "text_uthmani" : "قُلِ ٱللَّهُ أَعْلَمُ بِمَا لَبِثُوا۟ ۖ لَهُۥ غَيْبُ ٱلسَّمَـٰوَٰتِ وَٱلْأَرْضِ ۖ أَبْصِرْ بِهِۦ وَأَسْمِعْ ۚ مَا لَهُم مِّن دُونِهِۦ مِن وَلِىٍّ وَلَا يُشْرِكُ فِى حُكْمِهِۦٓ أَحَدًا",
    "chapter_id" : 18,
    "text_imlaei_simple" : "قل الله اعلم بما لبثوا له غيب السماوات والارض ابصر به واسمع ما لهم من دونه من ولي ولا يشرك في حكمه احدا",
    "page_number" : 296,
    "juz_number" : 15,
    "words" : [ {
      "id" : 28671,
      "position" : 1,
      "audio_url" : "wbw/018_026_001.mp3",
      "verse_key" : "18:26",
      "verse_id" : 2166,
      "location" : "18:26:1",
      "text_uthmani" : "قُلِ",
      "code_v1" : "ﯟ",
      "qpc_uthmani_hafs" : "قُلِ",
      "char_type_name" : "word",
      "page_number" : 296,
      "line_number" : 12,
      "text" : "ﯟ",
      "translation" : {
        "text" : "Say",
        "language_name" : "english",
        "language_id" : 38
      },
      "transliteration" : {
        "text" : "quli",
        "language_name" : "english",
        "language_id" : 38
      }
    }, {
      "id" : 28672,
      "position" : 2,
      "audio_url" : "wbw/018_026_002.mp3",
      "verse_key" : "18:26",
      "verse_id" : 2166,
      "location" : "18:26:2",
      "text_uthmani" : "ٱللَّهُ",
      "code_v1" : "ﯠ",
      "qpc_uthmani_hafs" : "ٱللَّهُ",
      "char_type_name" : "word",
      "page_number" : 296,
      "line_number" : 12,
      "text" : "ﯠ",
      "translation" : {
        "text" : "Allah",
        "language_name" : "english",
        "language_id" : 38
      },
      "transliteration" : {
        "text" : "l-lahu",
        "language_name" : "english",
        "language_id" : 38
      }
    }, {
      "id" : 28673,
      "position" : 3,
      "audio_url" : "wbw/018_026_003.mp3",
      "verse_key" : "18:26",
      "verse_id" : 2166,
      "location" : "18:26:3",
      "text_uthmani" : "أَعْلَمُ",
      "code_v1" : "ﯡ",
      "qpc_uthmani_hafs" : "أَعۡلَمُ",
      "char_type_name" : "word",
      "page_number" : 296,
      "line_number" : 12,
      "text" : "ﯡ",
      "translation" : {
        "text" : "knows best",
        "language_name" : "english",
        "language_id" : 38
      },
      "transliteration" : {
        "text" : "aʿlamu",
        "language_name" : "english",
        "language_id" : 38
      }
    }, {
      "id" : 28674,
      "position" : 4,
      "audio_url" : "wbw/018_026_004.mp3",
      "verse_key" : "18:26",
      "verse_id" : 2166,
      "location" : "18:26:4",
      "text_uthmani" : "بِمَا",
      "code_v1" : "ﯢ",
      "qpc_uthmani_hafs" : "بِمَا",
      "char_type_name" : "word",
      "page_number" : 296,
      "line_number" : 12,
      "text" : "ﯢ",
      "translation" : {
        "text" : "about what (period)",
        "language_name" : "english",
        "language_id" : 38
      },
      "transliteration" : {
        "text" : "bimā",
        "language_name" : "english",
        "language_id" : 38
      }
    }, {
      "id" : 28675,
      "position" : 5,
      "audio_url" : "wbw/018_026_005.mp3",
      "verse_key" : "18:26",
      "verse_id" : 2166,
      "location" : "18:26:5",
      "text_uthmani" : "لَبِثُوا۟ ۖ",
      "code_v1" : "ﯣﯤ",
      "qpc_uthmani_hafs" : "لَبِثُواْۖ",
      "char_type_name" : "word",
      "page_number" : 296,
      "line_number" : 12,
      "text" : "ﯣﯤ",
      "translation" : {
        "text" : "they remained",
        "language_name" : "english",
        "language_id" : 38
      },
      "transliteration" : {
        "text" : "labithū",
        "language_name" : "english",
        "language_id" : 38
      }
    }, {
      "id" : 28677,
      "position" : 6,
      "audio_url" : "wbw/018_026_007.mp3",
      "verse_key" : "18:26",
      "verse_id" : 2166,
      "location" : "18:26:6",
      "text_uthmani" : "لَهُۥ",
      "code_v1" : "ﯥ",
      "qpc_uthmani_hafs" : "لَهُۥ",
      "char_type_name" : "word",
      "page_number" : 296,
      "line_number" : 12,
      "text" : "ﯥ",
      "translation" : {
        "text" : "For Him",
        "language_name" : "english",
        "language_id" : 38
      },
      "transliteration" : {
        "text" : "lahu",
        "language_name" : "english",
        "language_id" : 38
      }
    }, {
      "id" : 28678,
      "position" : 7,
      "audio_url" : "wbw/018_026_008.mp3",
      "verse_key" : "18:26",
      "verse_id" : 2166,
      "location" : "18:26:7",
      "text_uthmani" : "غَيْبُ",
      "code_v1" : "ﯦ",
      "qpc_uthmani_hafs" : "غَيۡبُ",
      "char_type_name" : "word",
      "page_number" : 296,
      "line_number" : 12,
      "text" : "ﯦ",
      "translation" : {
        "text" : "(is the) unseen",
        "language_name" : "english",
        "language_id" : 38
      },
      "transliteration" : {
        "text" : "ghaybu",
        "language_name" : "english",
        "language_id" : 38
      }
    }, {
      "id" : 28679,
      "position" : 8,
      "audio_url" : "wbw/018_026_009.mp3",
      "verse_key" : "18:26",
      "verse_id" : 2166,
      "location" : "18:26:8",
      "text_uthmani" : "ٱلسَّمَـٰوَٰتِ",
      "code_v1" : "ﯧ",
      "qpc_uthmani_hafs" : "ٱلسَّمَٰوَٰتِ",
      "char_type_name" : "word",
      "page_number" : 296,
      "line_number" : 12,
      "text" : "ﯧ",
      "translation" : {
        "text" : "(of) the heavens",
        "language_name" : "english",
        "language_id" : 38
      },
      "transliteration" : {
        "text" : "l-samāwāti",
        "language_name" : "english",
        "language_id" : 38
      }
    }, {
      "id" : 28680,
      "position" : 9,
      "audio_url" : "wbw/018_026_010.mp3",
      "verse_key" : "18:26",
      "verse_id" : 2166,
      "location" : "18:26:9",
      "text_uthmani" : "وَٱلْأَرْضِ ۖ",
      "code_v1" : "ﯨﯩ",
      "qpc_uthmani_hafs" : "وَٱلۡأَرۡضِۖ",
      "char_type_name" : "word",
      "page_number" : 296,
      "line_number" : 12,
      "text" : "ﯨﯩ",
      "translation" : {
        "text" : "and the earth",
        "language_name" : "english",
        "language_id" : 38
      },
      "transliteration" : {
        "text" : "wal-arḍi",
        "language_name" : "english",
        "language_id" : 38
      }
    }, {
      "id" : 28682,
      "position" : 10,
      "audio_url" : "wbw/018_026_012.mp3",
      "verse_key" : "18:26",
      "verse_id" : 2166,
      "location" : "18:26:10",
      "text_uthmani" : "أَبْصِرْ",
      "code_v1" : "ﯪ",
      "qpc_uthmani_hafs" : "أَبۡصِرۡ",
      "char_type_name" : "word",
      "page_number" : 296,
      "line_number" : 13,
      "text" : "ﯪ",
      "translation" : {
        "text" : "How clearly He sees",
        "language_name" : "english",
        "language_id" : 38
      },
      "transliteration" : {
        "text" : "abṣir",
        "language_name" : "english",
        "language_id" : 38
      }
    }, {
      "id" : 28683,
      "position" : 11,
      "audio_url" : "wbw/018_026_013.mp3",
      "verse_key" : "18:26",
      "verse_id" : 2166,
      "location" : "18:26:11",
      "text_uthmani" : "بِهِۦ",
      "code_v1" : "ﯫ",
      "qpc_uthmani_hafs" : "بِهِۦ",
      "char_type_name" : "word",
      "page_number" : 296,
      "line_number" : 13,
      "text" : "ﯫ",
      "translation" : {
        "text" : "[of it]",
        "language_name" : "english",
        "language_id" : 38
      },
      "transliteration" : {
        "text" : "bihi",
        "language_name" : "english",
        "language_id" : 38
      }
    }, {
      "id" : 28684,
      "position" : 12,
      "audio_url" : "wbw/018_026_014.mp3",
      "verse_key" : "18:26",
      "verse_id" : 2166,
      "location" : "18:26:12",
      "text_uthmani" : "وَأَسْمِعْ ۚ",
      "code_v1" : "ﯬﯭ",
      "qpc_uthmani_hafs" : "وَأَسۡمِعۡۚ",
      "char_type_name" : "word",
      "page_number" : 296,
      "line_number" : 13,
      "text" : "ﯬﯭ",
      "translation" : {
        "text" : "And how clearly He hears",
        "language_name" : "english",
        "language_id" : 38
      },
      "transliteration" : {
        "text" : "wa-asmiʿ",
        "language_name" : "english",
        "language_id" : 38
      }
    }, {
      "id" : 28686,
      "position" : 13,
      "audio_url" : "wbw/018_026_016.mp3",
      "verse_key" : "18:26",
      "verse_id" : 2166,
      "location" : "18:26:13",
      "text_uthmani" : "مَا",
      "code_v1" : "ﯮ",
      "qpc_uthmani_hafs" : "مَا",
      "char_type_name" : "word",
      "page_number" : 296,
      "line_number" : 13,
      "text" : "ﯮ",
      "translation" : {
        "text" : "Not",
        "language_name" : "english",
        "language_id" : 38
      },
      "transliteration" : {
        "text" : "mā",
        "language_name" : "english",
        "language_id" : 38
      }
    }, {
      "id" : 28687,
      "position" : 14,
      "audio_url" : "wbw/018_026_017.mp3",
      "verse_key" : "18:26",
      "verse_id" : 2166,
      "location" : "18:26:14",
      "text_uthmani" : "لَهُم",
      "code_v1" : "ﯯ",
      "qpc_uthmani_hafs" : "لَهُم",
      "char_type_name" : "word",
      "page_number" : 296,
      "line_number" : 13,
      "text" : "ﯯ",
      "translation" : {
        "text" : "for them",
        "language_name" : "english",
        "language_id" : 38
      },
      "transliteration" : {
        "text" : "lahum",
        "language_name" : "english",
        "language_id" : 38
      }
    }, {
      "id" : 28688,
      "position" : 15,
      "audio_url" : "wbw/018_026_018.mp3",
      "verse_key" : "18:26",
      "verse_id" : 2166,
      "location" : "18:26:15",
      "text_uthmani" : "مِّن",
      "code_v1" : "ﯰ",
      "qpc_uthmani_hafs" : "مِّن",
      "char_type_name" : "word",
      "page_number" : 296,
      "line_number" : 13,
      "text" : "ﯰ",
      "translation" : {
        "text" : "besides Him",
        "language_name" : "english",
        "language_id" : 38
      },
      "transliteration" : {
        "text" : "min",
        "language_name" : "english",
        "language_id" : 38
      }
    }, {
      "id" : 28689,
      "position" : 16,
      "audio_url" : "wbw/018_026_019.mp3",
      "verse_key" : "18:26",
      "verse_id" : 2166,
      "location" : "18:26:16",
      "text_uthmani" : "دُونِهِۦ",
      "code_v1" : "ﯱ",
      "qpc_uthmani_hafs" : "دُونِهِۦ",
      "char_type_name" : "word",
      "page_number" : 296,
      "line_number" : 13,
      "text" : "ﯱ",
      "translation" : {
        "text" : "besides Him",
        "language_name" : "english",
        "language_id" : 38
      },
      "transliteration" : {
        "text" : "dūnihi",
        "language_name" : "english",
        "language_id" : 38
      }
    }, {
      "id" : 28690,
      "position" : 17,
      "audio_url" : "wbw/018_026_020.mp3",
      "verse_key" : "18:26",
      "verse_id" : 2166,
      "location" : "18:26:17",
      "text_uthmani" : "مِن",
      "code_v1" : "ﯲ",
      "qpc_uthmani_hafs" : "مِن",
      "char_type_name" : "word",
      "page_number" : 296,
      "line_number" : 13,
      "text" : "ﯲ",
      "translation" : {
        "text" : "any",
        "language_name" : "english",
        "language_id" : 38
      },
      "transliteration" : {
        "text" : "min",
        "language_name" : "english",
        "language_id" : 38
      }
    }, {
      "id" : 28691,
      "position" : 18,
      "audio_url" : "wbw/018_026_021.mp3",
      "verse_key" : "18:26",
      "verse_id" : 2166,
      "location" : "18:26:18",
      "text_uthmani" : "وَلِىٍّۢ",
      "code_v1" : "ﯳ",
      "qpc_uthmani_hafs" : "وَلِيّٖ",
      "char_type_name" : "word",
      "page_number" : 296,
      "line_number" : 13,
      "text" : "ﯳ",
      "translation" : {
        "text" : "protector",
        "language_name" : "english",
        "language_id" : 38
      },
      "transliteration" : {
        "text" : "waliyyin",
        "language_name" : "english",
        "language_id" : 38
      }
    }, {
      "id" : 28692,
      "position" : 19,
      "audio_url" : "wbw/018_026_022.mp3",
      "verse_key" : "18:26",
      "verse_id" : 2166,
      "location" : "18:26:19",
      "text_uthmani" : "وَلَا",
      "code_v1" : "ﯴ",
      "qpc_uthmani_hafs" : "وَلَا",
      "char_type_name" : "word",
      "page_number" : 296,
      "line_number" : 13,
      "text" : "ﯴ",
      "translation" : {
        "text" : "and not",
        "language_name" : "english",
        "language_id" : 38
      },
      "transliteration" : {
        "text" : "walā",
        "language_name" : "english",
        "language_id" : 38
      }
    }, {
      "id" : 28693,
      "position" : 20,
      "audio_url" : "wbw/018_026_023.mp3",
      "verse_key" : "18:26",
      "verse_id" : 2166,
      "location" : "18:26:20",
      "text_uthmani" : "يُشْرِكُ",
      "code_v1" : "ﯵ",
      "qpc_uthmani_hafs" : "يُشۡرِكُ",
      "char_type_name" : "word",
      "page_number" : 296,
      "line_number" : 13,
      "text" : "ﯵ",
      "translation" : {
        "text" : "He shares",
        "language_name" : "english",
        "language_id" : 38
      },
      "transliteration" : {
        "text" : "yush'riku",
        "language_name" : "english",
        "language_id" : 38
      }
    }, {
      "id" : 28694,
      "position" : 21,
      "audio_url" : "wbw/018_026_024.mp3",
      "verse_key" : "18:26",
      "verse_id" : 2166,
      "location" : "18:26:21",
      "text_uthmani" : "فِى",
      "code_v1" : "ﯶ",
      "qpc_uthmani_hafs" : "فِي",
      "char_type_name" : "word",
      "page_number" : 296,
      "line_number" : 14,
      "text" : "ﯶ",
      "translation" : {
        "text" : "[in]",
        "language_name" : "english",
        "language_id" : 38
      },
      "transliteration" : {
        "text" : "fī",
        "language_name" : "english",
        "language_id" : 38
      }
    }, {
      "id" : 28695,
      "position" : 22,
      "audio_url" : "wbw/018_026_025.mp3",
      "verse_key" : "18:26",
      "verse_id" : 2166,
      "location" : "18:26:22",
      "text_uthmani" : "حُكْمِهِۦٓ",
      "code_v1" : "ﯷ",
      "qpc_uthmani_hafs" : "حُكۡمِهِۦٓ",
      "char_type_name" : "word",
      "page_number" : 296,
      "line_number" : 14,
      "text" : "ﯷ",
      "translation" : {
        "text" : "His Commands",
        "language_name" : "english",
        "language_id" : 38
      },
      "transliteration" : {
        "text" : "ḥuk'mihi",
        "language_name" : "english",
        "language_id" : 38
      }
    }, {
      "id" : 28696,
      "position" : 23,
      "audio_url" : "wbw/018_026_026.mp3",
      "verse_key" : "18:26",
      "verse_id" : 2166,
      "location" : "18:26:23",
      "text_uthmani" : "أَحَدًۭا",
      "code_v1" : "ﯸ",
      "qpc_uthmani_hafs" : "أَحَدٗا",
      "char_type_name" : "word",
      "page_number" : 296,
      "line_number" : 14,
      "text" : "ﯸ",
      "translation" : {
        "text" : "(with) anyone",
        "language_name" : "english",
        "language_id" : 38
      },
      "transliteration" : {
        "text" : "aḥadan",
        "language_name" : "english",
        "language_id" : 38
      }
    }, {
      "id" : 28697,
      "position" : 24,
      "audio_url" : null,
      "verse_key" : "18:26",
      "verse_id" : 2166,
      "location" : "18:26:24",
      "text_uthmani" : "٢٦",
      "code_v1" : "ﯹ",
      "qpc_uthmani_hafs" : "٢٦",
      "char_type_name" : "end",
      "page_number" : 296,
      "line_number" : 14,
      "text" : "ﯹ",
      "translation" : {
        "text" : "(26)",
        "language_name" : "english",
        "language_id" : 38
      },
      "transliteration" : {
        "text" : null,
        "language_name" : "english",
        "language_id" : 38
      }
    } ]
  }, {
    "id" : 2167,
    "verse_number" : 27,
    "verse_key" : "18:27",
    "hizb_number" : 30,
    "rub_el_hizb_number" : 118,
    "ruku_number" : 255,
    "manzil_number" : 4,
    "sajdah_number" : null,
    "text_uthmani" : "وَٱتْلُ مَآ أُوحِىَ إِلَيْكَ مِن كِتَابِ رَبِّكَ ۖ لَا مُبَدِّلَ لِكَلِمَـٰتِهِۦ وَلَن تَجِدَ مِن دُونِهِۦ مُلْتَحَدًا",
    "chapter_id" : 18,
    "text_imlaei_simple" : "واتل ما اوحي اليك من كتاب ربك لا مبدل لكلماته ولن تجد من دونه ملتحدا",
    "page_number" : 296,
    "juz_number" : 15,
    "words" : [ {
      "id" : 29565,
      "position" : 1,
      "audio_url" : "wbw/018_027_001.mp3",
      "verse_key" : "18:27",
      "verse_id" : 2167,
      "location" : "18:27:1",
      "text_uthmani" : "وَٱتْلُ",
      "code_v1" : "ﯺ",
      "qpc_uthmani_hafs" : "وَٱتۡلُ",
      "char_type_name" : "word",
      "page_number" : 296,
      "line_number" : 14,
      "text" : "ﯺ",
      "translation" : {
        "text" : "And recite",
        "language_name" : "english",
        "language_id" : 38
      },
      "transliteration" : {
        "text" : "wa-ut'lu",
        "language_name" : "english",
        "language_id" : 38
      }
    }, {
      "id" : 29566,
      "position" : 2,
      "audio_url" : "wbw/018_027_002.mp3",
      "verse_key" : "18:27",
      "verse_id" : 2167,
      "location" : "18:27:2",
      "text_uthmani" : "مَآ",
      "code_v1" : "ﯻ",
      "qpc_uthmani_hafs" : "مَآ",
      "char_type_name" : "word",
      "page_number" : 296,
      "line_number" : 14,
      "text" : "ﯻ",
      "translation" : {
        "text" : "what",
        "language_name" : "english",
        "language_id" : 38
      },
      "transliteration" : {
        "text" : "mā",
        "language_name" : "english",
        "language_id" : 38
      }
    }, {
      "id" : 29567,
      "position" : 3,
      "audio_url" : "wbw/018_027_003.mp3",
      "verse_key" : "18:27",
      "verse_id" : 2167,
      "location" : "18:27:3",
      "text_uthmani" : "أُوحِىَ",
      "code_v1" : "ﯼ",
      "qpc_uthmani_hafs" : "أُوحِيَ",
      "char_type_name" : "word",
      "page_number" : 296,
      "line_number" : 14,
      "text" : "ﯼ",
      "translation" : {
        "text" : "has been revealed",
        "language_name" : "english",
        "language_id" : 38
      },
      "transliteration" : {
        "text" : "ūḥiya",
        "language_name" : "english",
        "language_id" : 38
      }
    }, {
      "id" : 29568,
      "position" : 4,
      "audio_url" : "wbw/018_027_004.mp3",
      "verse_key" : "18:27",
      "verse_id" : 2167,
      "location" : "18:27:4",
      "text_uthmani" : "إِلَيْكَ",
      "code_v1" : "ﯽ",
      "qpc_uthmani_hafs" : "إِلَيۡكَ",
      "char_type_name" : "word",
      "page_number" : 296,
      "line_number" : 14,
      "text" : "ﯽ",
      "translation" : {
        "text" : "to you",
        "language_name" : "english",
        "language_id" : 38
      },
      "transliteration" : {
        "text" : "ilayka",
        "language_name" : "english",
        "language_id" : 38
      }
    }, {
      "id" : 29569,
      "position" : 5,
      "audio_url" : "wbw/018_027_005.mp3",
      "verse_key" : "18:27",
      "verse_id" : 2167,
      "location" : "18:27:5",
      "text_uthmani" : "مِن",
      "code_v1" : "ﯾ",
      "qpc_uthmani_hafs" : "مِن",
      "char_type_name" : "word",
      "page_number" : 296,
      "line_number" : 14,
      "text" : "ﯾ",
      "translation" : {
        "text" : "of",
        "language_name" : "english",
        "language_id" : 38
      },
      "transliteration" : {
        "text" : "min",
        "language_name" : "english",
        "language_id" : 38
      }
    }, {
      "id" : 29570,
      "position" : 6,
      "audio_url" : "wbw/018_027_006.mp3",
      "verse_key" : "18:27",
      "verse_id" : 2167,
      "location" : "18:27:6",
      "text_uthmani" : "كِتَابِ",
      "code_v1" : "ﯿ",
      "qpc_uthmani_hafs" : "كِتَابِ",
      "char_type_name" : "word",
      "page_number" : 296,
      "line_number" : 14,
      "text" : "ﯿ",
      "translation" : {
        "text" : "the Book",
        "language_name" : "english",
        "language_id" : 38
      },
      "transliteration" : {
        "text" : "kitābi",
        "language_name" : "english",
        "language_id" : 38
      }
    }, {
      "id" : 29571,
      "position" : 7,
      "audio_url" : "wbw/018_027_007.mp3",
      "verse_key" : "18:27",
      "verse_id" : 2167,
      "location" : "18:27:7",
      "text_uthmani" : "رَبِّكَ ۖ",
      "code_v1" : "ﰀﰁ",
      "qpc_uthmani_hafs" : "رَبِّكَۖ",
      "char_type_name" : "word",
      "page_number" : 296,
      "line_number" : 15,
      "text" : "ﰀﰁ",
      "translation" : {
        "text" : "(of) your Lord",
        "language_name" : "english",
        "language_id" : 38
      },
      "transliteration" : {
        "text" : "rabbika",
        "language_name" : "english",
        "language_id" : 38
      }
    }, {
      "id" : 29573,
      "position" : 8,
      "audio_url" : "wbw/018_027_009.mp3",
      "verse_key" : "18:27",
      "verse_id" : 2167,
      "location" : "18:27:8",
      "text_uthmani" : "لَا",
      "code_v1" : "ﰂ",
      "qpc_uthmani_hafs" : "لَا",
      "char_type_name" : "word",
      "page_number" : 296,
      "line_number" : 15,
      "text" : "ﰂ",
      "translation" : {
        "text" : "None",
        "language_name" : "english",
        "language_id" : 38
      },
      "transliteration" : {
        "text" : "lā",
        "language_name" : "english",
        "language_id" : 38
      }
    }, {
      "id" : 29574,
      "position" : 9,
      "audio_url" : "wbw/018_027_010.mp3",
      "verse_key" : "18:27",
      "verse_id" : 2167,
      "location" : "18:27:9",
      "text_uthmani" : "مُبَدِّلَ",
      "code_v1" : "ﰃ",
      "qpc_uthmani_hafs" : "مُبَدِّلَ",
      "char_type_name" : "word",
      "page_number" : 296,
      "line_number" : 15,
      "text" : "ﰃ",
      "translation" : {
        "text" : "can change",
        "language_name" : "english",
        "language_id" : 38
      },
      "transliteration" : {
        "text" : "mubaddila",
        "language_name" : "english",
        "language_id" : 38
      }
    }, {
      "id" : 29575,
      "position" : 10,
      "audio_url" : "wbw/018_027_011.mp3",
      "verse_key" : "18:27",
      "verse_id" : 2167,
      "location" : "18:27:10",
      "text_uthmani" : "لِكَلِمَـٰتِهِۦ",
      "code_v1" : "ﰄ",
      "qpc_uthmani_hafs" : "لِكَلِمَٰتِهِۦ",
      "char_type_name" : "word",
      "page_number" : 296,
      "line_number" : 15,
      "text" : "ﰄ",
      "translation" : {
        "text" : "His Words",
        "language_name" : "english",
        "language_id" : 38
      },
      "transliteration" : {
        "text" : "likalimātihi",
        "language_name" : "english",
        "language_id" : 38
      }
    }, {
      "id" : 29576,
      "position" : 11,
      "audio_url" : "wbw/018_027_012.mp3",
      "verse_key" : "18:27",
      "verse_id" : 2167,
      "location" : "18:27:11",
      "text_uthmani" : "وَلَن",
      "code_v1" : "ﰅ",
      "qpc_uthmani_hafs" : "وَلَن",
      "char_type_name" : "word",
      "page_number" : 296,
      "line_number" : 15,
      "text" : "ﰅ",
      "translation" : {
        "text" : "and never",
        "language_name" : "english",
        "language_id" : 38
      },
      "transliteration" : {
        "text" : "walan",
        "language_name" : "english",
        "language_id" : 38
      }
    }, {
      "id" : 29577,
      "position" : 12,
      "audio_url" : "wbw/018_027_013.mp3",
      "verse_key" : "18:27",
      "verse_id" : 2167,
      "location" : "18:27:12",
      "text_uthmani" : "تَجِدَ",
      "code_v1" : "ﰆ",
      "qpc_uthmani_hafs" : "تَجِدَ",
      "char_type_name" : "word",
      "page_number" : 296,
      "line_number" : 15,
      "text" : "ﰆ",
      "translation" : {
        "text" : "you will find",
        "language_name" : "english",
        "language_id" : 38
      },
      "transliteration" : {
        "text" : "tajida",
        "language_name" : "english",
        "language_id" : 38
      }
    }, {
      "id" : 29578,
      "position" : 13,
      "audio_url" : "wbw/018_027_014.mp3",
      "verse_key" : "18:27",
      "verse_id" : 2167,
      "location" : "18:27:13",
      "text_uthmani" : "مِن",
      "code_v1" : "ﰇ",
      "qpc_uthmani_hafs" : "مِن",
      "char_type_name" : "word",
      "page_number" : 296,
      "line_number" : 15,
      "text" : "ﰇ",
      "translation" : {
        "text" : "besides Him",
        "language_name" : "english",
        "language_id" : 38
      },
      "transliteration" : {
        "text" : "min",
        "language_name" : "english",
        "language_id" : 38
      }
    }, {
      "id" : 29579,
      "position" : 14,
      "audio_url" : "wbw/018_027_015.mp3",
      "verse_key" : "18:27",
      "verse_id" : 2167,
      "location" : "18:27:14",
      "text_uthmani" : "دُونِهِۦ",
      "code_v1" : "ﰈ",
      "qpc_uthmani_hafs" : "دُونِهِۦ",
      "char_type_name" : "word",
      "page_number" : 296,
      "line_number" : 15,
      "text" : "ﰈ",
      "translation" : {
        "text" : "besides Him",
        "language_name" : "english",
        "language_id" : 38
      },
      "transliteration" : {
        "text" : "dūnihi",
        "language_name" : "english",
        "language_id" : 38
      }
    }, {
      "id" : 29580,
      "position" : 15,
      "audio_url" : "wbw/018_027_016.mp3",
      "verse_key" : "18:27",
      "verse_id" : 2167,
      "location" : "18:27:15",
      "text_uthmani" : "مُلْتَحَدًۭا",
      "code_v1" : "ﰉ",
      "qpc_uthmani_hafs" : "مُلۡتَحَدٗا",
      "char_type_name" : "word",
      "page_number" : 296,
      "line_number" : 15,
      "text" : "ﰉ",
      "translation" : {
        "text" : "a refuge",
        "language_name" : "english",
        "language_id" : 38
      },
      "transliteration" : {
        "text" : "mul'taḥadan",
        "language_name" : "english",
        "language_id" : 38
      }
    }, {
      "id" : 29581,
      "position" : 16,
      "audio_url" : null,
      "verse_key" : "18:27",
      "verse_id" : 2167,
      "location" : "18:27:16",
      "text_uthmani" : "٢٧",
      "code_v1" : "ﰊ",
      "qpc_uthmani_hafs" : "٢٧",
      "char_type_name" : "end",
      "page_number" : 296,
      "line_number" : 15,
      "text" : "ﰊ",
      "translation" : {
        "text" : "(27)",
        "language_name" : "english",
        "language_id" : 38
      },
      "transliteration" : {
        "text" : null,
        "language_name" : "english",
        "language_id" : 38
      }
    } ]
  } ],
  "pagination" : {
    "per_page" : 7,
    "current_page" : 1,
    "next_page" : null,
    "total_pages" : 1,
    "total_records" : 7
  }
}